Workbook

Sheet Raw Data Sales
A1: Serial No. | B1: Item Description | C1: Batch | D1: Quantity | E1: Supplier | F1: Date of Sale | G1: Expiration Date | H1: Cost Price | I1: M.R.P | J1: Selling Price | K1: Taxable Value | L1: SGST% | M1: SGST Amount | N1: CGST % | O1: CGST Amount | P1: Net Value
A2: 1 | B2: Dermadew Aloe Plus | C2: B028 | D2: 1 | E2: Ram Agencies | F2: 45931 | G2: 46478 | H2: 155.31818 | I2: 252 | J2: 170.85 | K2: 165.72 | L2: 9 | M2: 14.91 | N2: 9 | O2: 14.91 | P2: 195.54
A3: 2 | B3: Triluma Cream | C3: 5BD04 | D3: 2 | E3: Ram Agencies | F3: 45931 | G3: 46508 | H3: 546.1 | I3: 788.44 | J3: 600.71 | K3: 1165.38 | L3: 2.5 | M3: 29.13 | N3: 2.5 | O3: 29.13 | P3: 1223.64
A4: 3 | B4: Epilyno Lotion | C4: REP25005 | D4: 2 | E4: Ram Agencies | F4: 45931 | G4: 46478 | H4: 323.58182 | I4: 525 | J4: 355.94 | K4: 690.52 | L4: 9 | M4: 62.15 | N4: 9 | O4: 62.15 | P4: 814.82
A5: 4 | B5: Lulifin Cream | C5: SXG0407A | D5: 5 | E5: Ram Agencies | F5: 45931 | G5: 46388 | H5: 219.48182 | I5: 316.88 | J5: 241.43 | K5: 1170.94 | L5: 2.5 | M5: 29.27 | N5: 2.5 | O5: 29.27 | P5: 1229.48
A6: 5 | B6: Aziderm Plus Cream | C6: MAP054 | D6: 3 | E6: Ram Agencies | F6: 45931 | G6: 46508 | H6: 225.97273 | I6: 326.25 | J6: 248.57 | K6: 723.34 | L6: 2.5 | M6: 18.08 | N6: 2.5 | O6: 18.08 | P6: 759.5
A7: 6 | B7: Aquahance Moisture | C7: B022 | D7: 1 | E7: Ram Agencies | F7: 45931 | G7: 46631 | H7: 169.49091 | I7: 244.7 | J7: 186.44 | K7: 186.44 | L7: 9 | M7: 16.78 | N7: 9 | O7: 16.78 | P7: 220
A8: 7 | B8: Hhzole Cream | C8: C195 | D8: 1 | E8: Ram Agencies | F8: 45931 | G8: 46478 | H8: 146.1 | I8: 210.94 | J8: 160.71 | K8: 155.89 | L8: 2.5 | M8: 3.9 | N8: 2.5 | O8: 3.9 | P8: 163.69
A9: 8 | B9: Hhsone Cream | C9: HC161 | D9: 3 | E9: Ram Agencies | F9: 45931 | G9: 46478 | H9: 135.71818 | I9: 195.94 | J9: 149.29 | K9: 434.43 | L9: 2.5 | M9: 10.86 | N9: 2.5 | O9: 10.86 | P9: 456.15
A10: 9 | B10: Clonate Oint | C10: H352 | D10: 5 | E10: Ram Agencies | F10: 45931 | G10: 46508 | H10: 123.37273 | I10: 178.13 | J10: 135.71 | K10: 658.19 | L10: 2.5 | M10: 16.45 | N10: 2.5 | O10: 16.45 | P10: 691.09
A11: 10 | B11: Oflox-200 Tab | C11: 5SD0368 | D11: 5 | E11: Ram Agencies | F11: 45931 | G11: 46905 | H11: 69.581818 | I11: 100.46 | J11: 76.54 | K11: 334.1 | L11: 2.5 | M11: 8.35 | N11: 2.5 | O11: 8.35 | P11: 350.8
A12: 11 | B12: Ketafung CT Solution | C12: E3516 | D12: 1 | E12: Ram Agencies | F12: 45931 | G12: 46508 | H12: 218.67273 | I12: 315.69 | J12: 240.54 | K12: 233.32 | L12: 2.5 | M12: 5.83 | N12: 2.5 | O12: 5.83 | P12: 244.98
A13: 12 | B13: Strepsils Orange | C13: A1131 | D13: 1 | E13: Ram Agencies | F13: 45931 | G13: 46569 | H13: 572.72727 | I13: 787.5 | J13: 630 | K13: 630 | L13: 2.5 | M13: 15.75 | N13: 2.5 | O13: 15.75 | P13: 661.5
... A18: 17 | B18: Sompraz D Tab | C18: GTG1840B | D18: 3 | E18: Ram Agencies | F18: 45931 | G18: 46508 | H18: 172.08182 | I18: 248.44 | J18: 189.29 | K18: 550.83 | L18: 2.5 | M18: 13.77 | N18: 2.5 | O18: 13.77 | P18: 578.37
A19: 18 | B19: Azithral 500mg Tab | C19: 2508000966 | D19: 10 | E19: Ram Agencies | F19: 45931 | G19: 46539 | H19: 87.190909 | I19: 125.89 | J19: 95.91 | K19: 930.33 | L19: 2.5 | M19: 23.26 | N19: 2.5 | O19: 23.26 | P19: 976.85
A20: 19 | B20: Cyra -D Tabs | C20: 3CD1030 | D20: 10 | E20: Ram Agencies | F20: 45931 | G20: 46508 | H20: 33.118182 | I20: 47.81 | J20: 36.43 | K20: 353.37 | L20: 2.5 | M20: 8.83 | N20: 2.5 | O20: 8.83 | P20: 371.03
A21: 20 | B21: Tazloc Am Tabs | C21: 28026913 | D21: 10 | E21: Ram Agencies | F21: 45931 | G21: 46539 | H21: 104.13636 | I21: 150.35 | J21: 114.55 | K21: 1111.14 | L21: 2.5 | M21: 27.78 | N21: 2.5 | O21: 27.78 | P21: 1166.7
A22: 21 | B22: Mesacol Od Tabs | C22: GKG1103A | D22: 1 | E22: Ram Agencies | F22: 45931 | G22: 46508 | H22: 375.32727 | I22: 541.88 | J22: 412.86 | K22: 400.47 | L22: 2.5 | M22: 10.01 | N22: 2.5 | O22: 10.01 | P22: 420.49
A23: 22 | B23: Propysalic NF6 Ointment | C23: H1460 | D23: 5 | E23: Ram Agencies | F23: 45931 | G23: 46508 | H23: 135.71818 | I23: 195.94 | J23: 149.29 | K23: 724.06 | L23: 2.5 | M23: 18.1 | N23: 2.5 | O23: 18.1 | P23: 760.26
A24: 23 | B24: Concor Cor 2.5 Tabs | C24: M22AL25034 | D24: 3 | E24: Ram Agencies | F24: 45931 | G24: 46539 | H24: 61.336364 | I24: 88.55 | J24: 67.47 | K24: 196.34 | L24: 2.5 | M24: 4.91 | N24: 2.5 | O24: 4.91 | P24: 206.16
A25: 24 | B25: Clenz AC Topical Gel | C25: ZNC0029 | D25: 3 | E25: Ram Agencies | F25: 45931 | G25: 46478 | H25: 340.90909 | I25: 492.19 | J25: 375 | K25: 1091.25 | L25: 2.5 | M25: 27.28 | N25: 2.5 | O25: 27.28 | P25: 1145.81
A26: 25 | B26: Lulifin Cream | C26: SXG0341A | D26: 2 | E26: Ram Agencies | F26: 45932 | G26: 46388 | H26: 194.15455 | I26: 280.31 | J26: 213.57 | K26: 414.33 | L26: 2.5 | M26: 10.36 | N26: 2.5 | O26: 10.36 | P26: 435.05
A27: 26 | B27: Tedi Bar | C27: TD250628 | D27: 2 | E27: Ram Agencies | F27: 45932 | G27: 46508 | H27: 241.6 | I27: 392 | J27: 265.76 | K27: 515.57 | L27: 9 | M27: 46.4 | N27: 9 | O27: 46.4 | P27: 608.37
A28: 27 | B28: Aquahance Moisture | C28: B023 | D28: 2 | E28: Ram Agencies | F28: 45932 | G28: 46631 | H28: 169.49091 | I28: 244.7 | J28: 186.44 | K28: 361.69 | L28: 2.5 | M28: 9.04 | N28: 2.5 | O28: 9.04 | P28: 379.77
A29: 28 | B29: Seroflo-250 Inhaler | C29: 5SN0613 | D29: 1 | E29: Ram Agencies | F29: 45932 | G29: 46419 | H29: 633.58182 | I29: 914.73 | J29: 696.94 | K29: 676.03 | L29: 2.5 | M29: 16.9 | N29: 2.5 | O29: 16.9 | P29: 709.83
A30: 29 | B30: RotaHaler | C30: 03J25025 | D30: 1 | E30: Ram Agencies | F30: 45932 | G30: 47515 | H30: 120.29091 | I30: 173.52 | J30: 132.32 | K30: 128.24 | L30: 2.5 | M30: 3.21 | N30: 2.5 | O30: 3.21 | P30: 134.66
A31: 30 | B31: Dermadew Soap | C31: B364 | D31: 3 | E31: Ram Agencies | F31: 45932 | G31: 46905 | H31: 135.59091 | I31: 195.76 | J31: 149.15 | K31: 434.03 | L31: 2.5 | M31: 10.85 | N31: 2.5 | O31: 10.85 | P31: 455.73
A32: 31 | B32: Dermadew Baby Soap | C32: B296 | D32: 2 | E32: Ram Agencies | F32: 45932 | G32: 46905 | H32: 154.08182 | I32: 222.46 | J32: 169.49 | K32: 328.81 | L32: 2.5 | M32: 8.22 | N32: 2.5 | O32: 8.22 | P32: 345.25
A33: 32 | B33: Levolin Inhaler | C33: 5SN1165 | D33: 1 | E33: Ram Agencies | F33: 45932 | G33: 46266 | H33: 183.46364 | I33: 264.87 | J33: 201.81 | K33: 195.76 | L33: 2.5 | M33: 4.89 | N33: 2.5 | O33: 4.89 | P33: 205.54
... A59: 58 | B59: BuscoGast Tab | C59: BSA25021 | D59: 5 | E59: Mahaveer Medi Sales | F59: 45933 | G59: 46874 | H59: 30.272727 | I59: 41.63 | J59: 33.3 | K59: 161.51 | L59: 2.5 | M59: 4.04 | N59: 2.5 | O59: 4.04 | P59: 169.58
A60: 59 | B60: Sebum Clear N Gel | C60: 5038 | D60: 5 | E60: Mahaveer Medi Sales | F60: 45933 | G60: 46478 | H60: 220.78182 | I60: 340 | J60: 242.86 | K60: 1177.87 | L60: 2.5 | M60: 29.45 | N60: 2.5 | O60: 29.45 | P60: 1236.77
A61: 60 | B61: Clincitop Gel | C61: E25161S | D61: 1 | E61: Mahaveer Medi Sales | F61: 45933 | G61: 46478 | H61: 25.227273 | I61: 57.09 | J61: 27.75 | K61: 27.75 | L61: 2.5 | M61: 0.69 | N61: 2.5 | O61: 0.69 | P61: 29.13
A62: 61 | B62: Sebamed Baby Cream Extra | C62: 5A147A24 | D62: 2 | E62: Mahaveer Medi Sales | F62: 45933 | G62: 46905 | H62: 173.34545 | I62: 270 | J62: 190.68 | K62: 381.36 | L62: 9 | M62: 34.32 | N62: 9 | O62: 34.32 | P62: 450
A63: 62 | B63: Zocon-200 mg Tab© | C63: 075C043 | D63: 5 | E63: Mahaveer Medi Sales | F63: 45933 | G63: 46784 | H63: 51.663636 | I63: 74.59 | J63: 56.83 | K63: 275.63 | L63: 2.5 | M63: 6.89 | N63: 2.5 | O63: 6.89 | P63: 289.41
A64: 63 | B64: Hycort Cream | C64: HY20 | D64: 10 | E64: Avenues Pharma | F64: 45933 | G64: 46508 | H64: 119.1 | I64: 165 | J64: 131.01 | K64: 1270.8 | L64: 2.5 | M64: 31.77 | N64: 2.5 | O64: 31.77 | P64: 1334.34
A65: 64 | B65: C-Facewash | C65: 34013090 | D65: 12 | E65: Cosmonova Medicare | F65: 45933 | G65: 46539 | H65: 246.53636 | I65: 400 | J65: 271.19 | K65: 2711.9 | L65: 9 | M65: 244.07 | N65: 9 | O65: 244.07 | P65: 3200
A66: 65 | B66: Minfin NX 5% | C66: THMNX2502 | D66: 5 | E66: Medline Distributors | F66: 45933 | G66: 46478 | H66: 616.88182 | I66: 890.63 | J66: 678.57 | K66: 3291.06 | L66: 2.5 | M66: 164.56 | N66: 2.5 | O66: 164.56 | P66: 3455.62
A67: 66 | B67: Minfin MAXX 5% | C67: THMM-2505 | D67: 5 | E67: Medline Distributors | F67: 45933 | G67: 46478 | H67: 603.24545 | I67: 870.94 | J67: 663.57 | K67: 3218.31 | L67: 2.5 | M67: 160.92 | N67: 2.5 | O67: 160.92 | P67: 3379.23
A68: 67 | B68: Castor NF Cream | C68: DLWH5153 | D68: 1 | E68: Mahaveer Medi Sales | F68: 45933 | G68: 46539 | H68: 32.727273 | I68: 112 | J68: 36 | K68: 36 | L68: 2.5 | M68: 0.9 | N68: 2.5 | O68: 0.9 | P68: 37.8
A69: 68 | B69: Depiwhite eye gel | C69: E25B01 | D69: 1 | E69: Mahaveer Medi Sales | F69: 45933 | G69: 46784 | H69: 459.78182 | I69: 746 | J69: 505.76 | K69: 490.59 | L69: 9 | M69: 44.15 | N69: 9 | O69: 44.15 | P69: 578.89
A70: 69 | B70: Lacto Calamine Oily Skin | C70: DACF057 | D70: 1 | E70: Mahaveer Medi Sales | F70: 45933 | G70: 46874 | H70: 178.28182 | I70: 260 | J70: 196.11 | K70: 196.11 | L70: 9 | M70: 17.15 | N70: 9 | O70: 17.15 | P70: 231.41
A71: 70 | B71: Hairtamin Cap | C71: INC2598 | D71: 1 | E71: Mahaveer Medi Sales | F71: 45933 | G71: 46388 | H71: 154.08182 | I71: 222.46 | J71: 169.49 | K71: 164.41 | L71: 2.5 | M71: 4.11 | N71: 2.5 | O71: 4.11 | P71: 172.63
A72: 71 | B72: Hairtamin Cap | C72: INC2563 | D72: 1 | E72: Mahaveer Medi Sales | F72: 45933 | G72: 46327 | H72: 154.08182 | I72: 222.46 | J72: 169.49 | K72: 164.41 | L72: 2.5 | M72: 4.11 | N72: 2.5 | O72: 4.11 | P72: 172.63
A73: 72 | B73: Momentsone Cream | C73: AH921 | D73: 3 | E73: RSM Pharma | F73: 45933 | G73: 46508 | H73: 238 | I73: 328.13 | J73: 261.8 | K73: 761.84 | L73: 2.5 | M73: 19.05 | N73: 2.5 | O73: 19.05 | P73: 799.94
A74: 73 | B74: Pantocid IT Caps | C74: SIG0703A | D74: 2 | E74: RSM Pharma | F74: 45933 | G74: 46419 | H74: 238.96364 | I74: 345 | J74: 262.86 | K74: 509.95 | L74: 2.5 | M74: 12.75 | N74: 2.5 | O74: 12.75 | P74: 535.45
A75: 74 | B75: Hhomega + Cap | C75: SF25078 | D75: 6 | E75: RSM Pharma | F75: 45933 | G75: 46508 | H75: 141.76364 | I75: 204.66 | J75: 155.94 | K75: 907.57 | L75: 2.5 | M75: 22.69 | N75: 2.5 | O75: 22.69 | P75: 952.95
A76: 75 | B76: Stolin R Active Toothpaste | C76: STR25025 | D76: 1 | E76: RSM Pharma | F76: 45933 | G76: 46478 | H76: 160.24545 | I76: 231.36 | J76: 176.27 | K76: 170.98 | L76: 2.5 | M76: 4.27 | N76: 2.5 | O76: 4.27 | P76: 179.52
A77: 76 | B77: Olmesar Ch 20MG Tab | C77: 18251018A | D77: 2 | E77: RSM Pharma | F77: 45933 | G77: 46784 | H77: 147.85455 | I77: 213.47 | J77: 162.64 | K77: 315.52 | L77: 2.5 | M77: 7.89 | N77: 2.5 | O77: 7.89 | P77: 331.3
... A145: 144 | B145: Nurokind Gold RF Caps | C145: B12Y075 | D145: 1 | E145: Ram Agencies | F145: 45936 | G145: 46327 | H145: 67.709091 | I145: 103.01 | J145: 74.48 | K145: 72.25 | L145: 2.5 | M145: 1.81 | N145: 2.5 | O145: 1.81 | P145: 75.87
A146: 145 | B146: Candid Cream | C146: 11230179 | D146: 6 | E146: Ram Agencies | F146: 45936 | G146: 46388 | H146: 65.454545 | I146: 94.5 | J146: 72 | K146: 384.12 | L146: 2.5 | M146: 9.6 | N146: 2.5 | O146: 9.6 | P146: 403.32
A147: 146 | B147: Patchex Tab | C147: 657SPL2505F | D147: 1 | E147: Ram Agencies | F147: 45936 | G147: 46478 | H147: 268.10909 | I147: 387.08 | J147: 294.92 | K147: 286.07 | L147: 2.5 | M147: 7.15 | N147: 2.5 | O147: 7.15 | P147: 300.32
A148: 147 | B148: Patchex Tab | C148: 657SPL2505F | D148: 1 | E148: Ram Agencies | F148: 45936 | G148: 46478 | H148: 268.05455 | I148: 387 | J148: 294.86 | K148: 286.01 | L148: 2.5 | M148: 7.15 | N148: 2.5 | O148: 7.15 | P148: 300.32
A149: 148 | B149: Renerve Plus Caps | C149: GRE625092 | D149: 1 | E149: Ram Agencies | F149: 45936 | G149: 46539 | H149: 207.55455 | I149: 299.66 | J149: 228.31 | K149: 221.46 | L149: 2.5 | M149: 5.54 | N149: 2.5 | O149: 5.54 | P149: 232.54
A150: 149 | B150: Vantej Aqua Mouthwash | C150: ABAA103 | D150: 1 | E150: Ram Agencies | F150: 45936 | G150: 46569 | H150: 111.86364 | I150: 181.5 | J150: 123.05 | K150: 119.36 | L150: 9 | M150: 10.74 | N150: 9 | O150: 10.74 | P150: 140.84
A151: 150 | B151: Pan D Capsules | C151: 25442349 | D151: 10 | E151: Ram Agencies | F151: 45936 | G151: 46508 | H151: 164.91818 | I151: 238.1 | J151: 181.41 | K151: 1759.68 | L151: 2.5 | M151: 43.99 | N151: 2.5 | O151: 43.99 | P151: 1847.66
A152: 151 | B152: Zerodol SP Tabs | C152: FND0725062BH | D152: 10 | E152: Ram Agencies | F152: 45936 | G152: 46722 | H152: 96.754545 | I152: 139.69 | J152: 106.43 | K152: 1032.37 | L152: 2.5 | M152: 25.81 | N152: 2.5 | O152: 25.81 | P152: 1083.93
A153: 152 | B153: Telmikind 20 | C153: IO5Y007 | D153: 3 | E153: RSM Pharma | F153: 45937 | G153: 46478 | H153: 17.618182 | I153: 25.44 | J153: 19.38 | K153: 56.4 | L153: 2.5 | M153: 1.41 | N153: 2.5 | O153: 1.41 | P153: 59.22
A154: 153 | B154: ORSL Apple Rehydrate Drink | C154: SK50053 | D154: 25 | E154: RSM Pharma | F154: 45937 | G154: 46235 | H154: 32.418182 | I154: 46.8 | J154: 35.66 | K154: 891.5 | L154: 2.5 | M154: 22.275 | N154: 2.5 | O154: 22.275 | P154: 936.05
A155: 154 | B155: Imograf Ointment | C155: 5337 | D155: 2 | E155: RSM Pharma | F155: 45937 | G155: 46478 | H155: 103.9 | I155: 150 | J155: 114.29 | K155: 221.72 | L155: 2.5 | M155: 5.54 | N155: 2.5 | O155: 5.54 | P155: 232.8
A156: 155 | B156: Ebruma Cream | C156: AH913 | D156: 2 | E156: RSM Pharma | F156: 45937 | G156: 46508 | H156: 374 | I156: 515.63 | J156: 411.4 | K156: 798.12 | L156: 2.5 | M156: 19.95 | N156: 2.5 | O156: 19.95 | P156: 838.02
A157: 156 | B157: Clavam 625 MG | C157: 25442309 | D157: 1 | E157: RSM Pharma | F157: 45937 | G157: 46327 | H157: 135.39091 | I157: 195.47 | J157: 148.93 | K157: 144.46 | L157: 2.5 | M157: 3.61 | N157: 2.5 | O157: 3.61 | P157: 151.68
A158: 157 | B158: Patchex Tab | C158: 657SPL2505F | D158: 2 | E158: RSM Pharma | F158: 45937 | G158: 46357 | H158: 268.10909 | I158: 387.08 | J158: 294.92 | K158: 572.14 | L158: 2.5 | M158: 14.3 | N158: 2.5 | O158: 14.3 | P158: 600.74
A159: 158 | B159: Trinicalm Plus Tab | C159: 2F79M005 | D159: 15 | E159: RSM Pharma | F159: 45937 | G159: 46905 | H159: 21.036364 | I159: 30.37 | J159: 23.14 | K159: 336.69 | L159: 2.5 | M159: 8.42 | N159: 2.5 | O159: 8.42 | P159: 353.53
A160: 159 | B160: Trivolib 1MG Tab | C160: ZFC0089 | D160: 3 | E160: RSM Pharma | F160: 45937 | G160: 46874 | H160: 172.08182 | I160: 248.44 | J160: 189.29 | K160: 550.83 | L160: 2.5 | M160: 13.77 | N160: 2.5 | O160: 13.77 | P160: 578.37
A161: 160 | B161: Ascoril LS SYP | C161: 05250729A | D161: 7 | E161: RSM Pharma | F161: 45937 | G161: 46478 | H161: 100.32727 | I161: 144.85 | J161: 110.36 | K161: 701.17 | L161: 2.5 | M161: 17.53 | N161: 2.5 | O161: 17.53 | P161: 736.23
A162: 161 | B162: Sensodent K (150ML) | C162: 25BM0001 | D162: 2 | E162: Mahaveer Medi Sales | F162: 45937 | G162: 46722 | H162: 88.963636 | I162: 137 | J162: 97.86 | K162: 189.85 | L162: 2.5 | M162: 4.25 | N162: 2.5 | O162: 4.25 | P162: 199.35
A163: 162 | B163: No Scars Cream 20GM | C163: B2952019 | D163: 1 | E163: Mahaveer Medi Sales | F163: 45937 | G163: 46388 | H163: 166.36364 | I163: 246.56 | J163: 183 | K163: 183 | L163: 2.5 | M163: 4.58 | N163: 2.5 | O163: 4.58 | P163: 192.16
A164: 163 | B164: Flawlizo Micro 0.1% Gel | C164: 5QD01 | D164: 1 | E164: Mahaveer Medi Sales | F164: 45937 | G164: 46478 | H164: 448.05455 | I164: 646.88 | J164: 492.86 | K164: 478.07 | L164: 2.5 | M164: 11.95 | N164: 2.5 | O164: 11.95 | P164: 501.97
A165: 164 | B165: Cheston Cold Total Tab | C165: M250341 | D165: 10 | E165: Mahaveer Medi Sales | F165: 45937 | G165: 46419 | H165: 47.5 | I165: 115 | J165: 52.25 | K165: 522.5 | L165: 2.5 | M165: 13.06 | N165: 2.5 | O165: 13.06 | P165: 548.62
A166: 165 | B166: Mindruff Scalp Solution | C166: YBM-2501 | D166: 2 | E166: Avenues Pharma | F166: 45938 | G166: 46784 | H166: 321.42727 | I166: 464.06 | J166: 353.57 | K166: =P166-M166-O166 -> 685.95 | L166: 2.5 | M166: 17.14 | N166: 2.5 | O166: 17.14 | P166: 720.23
A167: 166 | B167: Ebruma Cream | C167: AH913 | D167: 2 | E167: Avenues Pharma | F167: 45938 | G167: 46508 | H167: 374 | I167: 515.63 | J167: 411.4 | K167: =P167-M167-O167 -> 798.11 | L167: 2.5 | M167: 19.955 | N167: 2.5 | O167: 19.955 | P167: 838.02
A168: 167 | B168: Lulikite Cream | C168: AH928 | D168: 2 | E168: Avenues Pharma | F168: 45938 | G168: 46508 | H168: 407.31818 | I168: 561.56 | J168: 448.05 | K168: =P168-M168-O168 -> 869.22 | L168: 2.5 | M168: 21.73 | N168: 2.5 | O168: 21.73 | P168: 912.68
A169: 168 | B169: Glykind 60 XR Tab | C169: E5GKY005 | D169: 3 | E169: Ram Agencies | F169: 45938 | G169: 46478 | H169: 63.218182 | I169: 91.27 | J169: 69.54 | K169: 202.36 | L169: 2.5 | M169: 5.06 | N169: 2.5 | O169: 5.06 | P169: 212.48
A170: 169 | B170: Olmezest AM 40MG Tabs | C170: SIG1122A | D170: 5 | E170: Ram Agencies | F170: 45938 | G170: 46478 | H170: 188.30909 | I170: 271.88 | J170: 207.14 | K170: 1004.63 | L170: 2.5 | M170: 25.12 | N170: 2.5 | O170: 25.12 | P170: 1054.87
A171: 170 | B171: Tazloc Beta 25MG Tabs | C171: TBF14 | D171: 10 | E171: Ram Agencies | F171: 45938 | G171: 46508 | H171: 133.76364 | I171: 193.13 | J171: 147.14 | K171: 1427.26 | L171: 2.5 | M171: 35.68 | N171: 2.5 | O171: 35.68 | P171: 1498.62
A172: 171 | B172: Pilex Tabs | C172: 111250908 | D172: 1 | E172: Ram Agencies | F172: 45938 | G172: 46905 | H172: 162.07273 | I172: 234 | J172: 178.28 | K172: 172.93 | L172: 2.5 | M172: 4.32 | N172: 2.5 | O172: 4.32 | P172: 181.57
A173: 172 | B173: Reclide 40 Tablets | C173: E2501244 | D173: 4 | E173: Ram Agencies | F173: 45938 | G173: 46905 | H173: 56 | I173: 80.85 | J173: 61.6 | K173: 239.01 | L173: 2.5 | M173: 5.98 | N173: 2.5 | O173: 5.98 | P173: 250.97
A174: 173 | B174: Mox 250MG Redimix 60ML | C174: DFG4574A | D174: 1 | E174: Ram Agencies | F174: 45938 | G174: 46357 | H174: 69.181818 | I174: 99.88 | J174: 76.1 | K174: 73.82 | L174: 2.5 | M174: 1.85 | N174: 2.5 | O174: 1.85 | P174: 77.52
A175: 174 | B175: Telemikind-H 80 Tabs | C175: B25Y008 | D175: 1 | E175: Ram Agencies | F175: 45938 | G175: 46388 | H175: 97.745455 | I175: 141.12 | J175: 107.52 | K175: 104.29 | L175: 2.5 | M175: 2.61 | N175: 2.5 | O175: 2.61 | P175: 109.51
A176: 175 | B176: Naprosyn+250MG 15S | C176: 24N25011 | D176: 2 | E176: Ram Agencies | F176: 45938 | G176: 46874 | H176: 75.127273 | I176: 108.46 | J176: 82.64 | K176: 160.32 | L176: 2.5 | M176: 4.01 | N176: 2.5 | O176: 4.01 | P176: 168.34
A177: 176 | B177: Glycomet GP 1 Tabs | C177: 60002196 | D177: 10 | E177: Ram Agencies | F177: 45938 | G177: 46539 | H177: 85.390909 | I177: 123.28 | J177: 93.93 | K177: 911.12 | L177: 2.5 | M177: 22.78 | N177: 2.5 | O177: 22.78 | P177: 956.68
A178: 177 | B178: Nurokind LC Tabs | C178: B95Y072 | D178: 6 | E178: Ram Agencies | F178: 45938 | G178: 46508 | H178: 165.48182 | I178: 238.91 | J178: 182.03 | K178: 971.13 | L178: 2.5 | M178: 24.28 | N178: 2.5 | O178: 24.28 | P178: 1019.69
A179: 178 | B179: Tenepride 20 Tabs | C179: TNAS0134 | D179: 2 | E179: Ram Agencies | F179: 45938 | G179: 46357 | H179: 241.94545 | I179: 349.3 | J179: 266.14 | K179: 516.31 | L179: 2.5 | M179: 12.91 | N179: 2.5 | O179: 12.91 | P179: 542.13
A180: 179 | B180: Shelcal 500 Tabs | C180: 8LV2M237 | D180: 5 | E180: Ram Agencies | F180: 45938 | G180: 46478 | H180: 102.96364 | I180: 148.65 | J180: 113.26 | K180: 549.31 | L180: 2.5 | M180: 13.73 | N180: 2.5 | O180: 13.73 | P180: 576.77
A181: 180 | B181: Duphalac Syrup | C181: 793178D7 | D181: 2 | E181: Ram Agencies | F181: 45938 | G181: 46508 | H181: 136.36364 | I181: 196.87 | J181: 150 | K181: 291 | L181: 2.5 | M181: 7.28 | N181: 2.5 | O181: 7.28 | P181: 305.56
A182: 181 | B182: Beatdine 0.2% | C182: GF01825 | D182: 1 | E182: Ram Agencies | F182: 45938 | G182: 46327 | H182: 216.88182 | I182: 313.13 | J182: 238.57 | K182: 231.41 | L182: 2.5 | M182: 5.79 | N182: 2.5 | O182: 5.79 | P182: 242.99
A183: 182 | B183: Lacryl Hydrate Eye Drops | C183: 25DB18 | D183: 3 | E183: RSM Pharma | F183: 45938 | G183: 46388 | H183: 357.79091 | I183: 516.56 | J183: 393.57 | K183: 1145.29 | L183: 2.5 | M183: 28.61 | N183: 2.5 | O183: 28.61 | P183: 1202.55
A184: 183 | B184: Lulipex Cream | C184: LPC2503 | D184: 1 | E184: RSM Pharma | F184: 45938 | G184: 46508 | H184: 92.527273 | I184: 133.59 | J184: 101.78 | K184: 98.73 | L184: 2.5 | M184: 2.47 | N184: 2.5 | O184: 2.47 | P184: 103.67
A185: 184 | B185: EBAL 20 | C185: EBE29 | D185: 10 | E185: RSM Pharma | F185: 45938 | G185: 46508 | H185: 74.354545 | I185: 107.34 | J185: 81.79 | K185: 793.36 | L185: 2.5 | M185: 19.83 | N185: 2.5 | O185: 19.83 | P185: 833.02
A186: 185 | B186: Beatdine Gargle 2% Mint | C186: GD020250 | D186: 1 | E186: RSM Pharma | F186: 45938 | G186: 46266 | H186: 216.88182 | I186: 313.13 | J186: 238.57 | K186: 231.41 | L186: 2.5 | M186: 5.79 | N186: 2.5 | O186: 5.79 | P186: 242.99
A187: 186 | B187: Cardace 5mg Tab | C187: 4NG023 | D187: 2 | E187: RSM Pharma | F187: 45938 | G187: 46631 | H187: 89.236364 | I187: 128.83 | J187: 98.16 | K187: 190.43 | L187: 2.5 | M187: 4.76 | N187: 2.5 | O187: 4.76 | P187: 199.95
A188: 187 | B188: Kailas Jeevan Cream | C188: 403 | D188: 1 | E188: RSM Pharma | F188: 45938 | G188: 46874 | H188: 44.845455 | I188: 60.94 | J188: 49.33 | K188: 49.33 | L188: 2.5 | M188: 1.23 | N188: 2.5 | O188: 1.23 | P188: 51.79
A189: 188 | B189: Seroflo-250 Inhaler | C189: 5SN0611 | D189: 1 | E189: RSM Pharma | F189: 45938 | G189: 46419 | H189: 633.58182 | I189: 914.74 | J189: 696.94 | K189: 676.03 | L189: 2.5 | M189: 16.9 | N189: 2.5 | O189: 16.9 | P189: 709.83
A190: 189 | B190: Dermadew PMX Anti itch Lotion | C190: B011 | D190: 2 | E190: RSM Pharma | F190: 45938 | G190: 46539 | H190: 292.75455 | I190: 475 | J190: 322.03 | K190: 152.43 | L190: 2.5 | M190: 56.23 | N190: 2.5 | O190: 56.23 | P190: 737.2
A191: 190 | B191: Rozat 5MG Tab | C191: E2501268 | D191: 2 | E191: RSM Pharma | F191: 45938 | G191: 46508 | H191: 118.18182 | I191: 170.63 | J191: 130 | K191: 252.2 | L191: 2.5 | M191: 6.31 | N191: 2.5 | O191: 6.31 | P191: 264.82
A192: 191 | B192: Picon Cream 10gm | C192: DJ065 | D192: 2 | E192: RSM Pharma | F192: 45938 | G192: 46539 | H192: 457.85455 | I192: 661.03 | J192: 503.64 | K192: 977.06 | L192: 2.5 | M192: 24.43 | N192: 2.5 | O192: 24.43 | P192: 1025.92
A193: 192 | B193: Kailas Jeevan Cream | C193: 402 | D193: 2 | E193: RSM Pharma | F193: 45938 | G193: 46874 | H193: 103.49091 | I193: 140.63 | J193: 113.84 | K193: 227.68 | L193: 2.5 | M193: 5.69 | N193: 2.5 | O193: 5.69 | P193: 239.06
A194: 193 | B194: Dazit 10MG Tab | C194: GTG1398A | D194: 4 | E194: RSM Pharma | F194: 45938 | G194: 46478 | H194: 182.46364 | I194: 263.44 | J194: 200.71 | K194: 778.75 | L194: 2.5 | M194: 19.47 | N194: 2.5 | O194: 19.47 | P194: 817.69
A195: 194 | B195: Tyza M Cream | C195: UF003 | D195: 5 | E195: RSM Pharma | F195: 45938 | G195: 46478 | H195: 86.754545 | I195: 125.25 | J195: 95.43 | K195: 462.84 | L195: 2.5 | M195: 11.57 | N195: 2.5 | O195: 11.57 | P195: 485.98
A196: 195 | B196: Candid Cream | C196: 11240179 | D196: 1 | E196: RSM Pharma | F196: 45938 | G196: 46388 | H196: 65.454545 | I196: 94.5 | J196: 72 | K196: 69.84 | L196: 2.5 | M196: 1.75 | N196: 2.5 | O196: 1.75 | P196: 485.98
...

Sheet Raw Data Expiry Date
A1: Serial No. | B1: Item Description | C1: Quantity | D1: Manufacture date | E1: Expiry Date | F1: MRP
A2: 1 | B2: Lecmon-AM | C2: 15 | D2: 45200 | E2: 45901 | F2: 169
A3: 2 | B3: Proanagen Tabs | C3: 5 | D3: 45231 | E3: 45962 | F3: 263
A4: 3 | B4: Xaliderm Solution | C4: 35 | D4: 44896 | E4: 45962 | F4: 299
A5: 4 | B5: Everolimus | C5: 25 | D5: 45292 | E5: 45992 | F5: 191.66
A6: 5 | B6: Prednisone | C6: 15 | D6: 45261 | E6: 45962 | F6: 70.56
A7: 6 | B7: Terbinaforce 500 | C7: 10 | D7: 45231 | E7: 45839 | F7: 184.47
A8: 7 | B8: Methylprednisolone | C8: 15 | D8: 45108 | E8: 45992 | F8: 143.37
A9: 8 | B9: Ocid 20 | C9: 10 | D9: 45292 | E9: 45901 | F9: 64.28
A10: 9 | B10: Tacrolimus | C10: 8 | D10: 44958 | E10: 46023 | F10: 249
A11: 10 | B11: Metsmall 500 | C11: 9 | D11: 44896 | E11: 45962 | F11: 54
A12: 11 | B12: Cyclosporine | C12: 20 | D12: 44927 | E12: 45992 | F12: 32.04
A13: 12 | B13: Infliximab | C13: 9 | D13: 45323 | E13: 45809 | F13: 64.96
... A46: 45 | B46: Tenolol 50MG | C46: 20 | D46: 45292 | E46: 45901 | F46: 35

Sheet Sheet6

Sheet Cleaned data Sales
A1: Serial No. | B1: Item Description | C1: Category | D1: Quantity | E1: Supplier | F1: Date of Sale | G1: Cost Price | H1: Selling Price | I1: Net Value | J1: Profit per product | K1: Total Profit
A2: 1 | B2: Dermadew Aloe Plus | C2: Skincare | D2: 1 | E2: Ram Agencies | F2: 45931 | G2: 155.31818 | H2: 170.85 | I2: 195.54 | J2: =H2-G2 -> 15.531818 | K2: =J2*D2 -> 15.531818
A3: 2 | B3: Triluma Cream | C3: Skincare | D3: 2 | E3: Ram Agencies | F3: 45931 | G3: 546.1 | H3: 600.71 | I3: 1223.64 | J3: =H3-G3 -> 54.61 | K3: =J3*D3 -> 109.22
A4: 3 | B4: Epilyno Lotion | C4: Skincare | D4: 2 | E4: Ram Agencies | F4: 45931 | G4: 323.58182 | H4: 355.94 | I4: 814.82 | J4: =H4-G4 -> 32.358182 | K4: =J4*D4 -> 64.716364
A5: 4 | B5: Lulifin Cream | C5: Anti-microbial | D5: 5 | E5: Ram Agencies | F5: 45931 | G5: 219.48182 | H5: 241.43 | I5: 1229.48 | J5: =H5-G5 -> 21.948182 | K5: =J5*D5 -> 109.74091
A6: 5 | B6: Aziderm Plus Cream | C6: Skincare | D6: 3 | E6: Ram Agencies | F6: 45931 | G6: 225.97273 | H6: 248.57 | I6: 759.5 | J6: =H6-G6 -> 22.597273 | K6: =J6*D6 -> 67.791818
A7: 6 | B7: Aquahance Moisture | C7: Skincare | D7: 1 | E7: Ram Agencies | F7: 45931 | G7: 169.49091 | H7: 186.44 | I7: 220 | J7: =H7-G7 -> 16.949091 | K7: =J7*D7 -> 16.949091
A8: 7 | B8: Hhzole Cream | C8: Anti-microbial | D8: 1 | E8: Ram Agencies | F8: 45931 | G8: 146.1 | H8: 160.71 | I8: 163.69 | J8: =H8-G8 -> 14.61 | K8: =J8*D8 -> 14.61
A9: 8 | B9: Hhsone Cream | C9: Anti-microbial | D9: 3 | E9: Ram Agencies | F9: 45931 | G9: 135.71818 | H9: 149.29 | I9: 456.15 | J9: =H9-G9 -> 13.571818 | K9: =J9*D9 -> 40.715455
A10: 9 | B10: Clonate Oint | C10: Anti-microbial | D10: 5 | E10: Ram Agencies | F10: 45931 | G10: 123.37273 | H10: 135.71 | I10: 691.09 | J10: =H10-G10 -> 12.337273 | K10: =J10*D10 -> 61.686364
A11: 10 | B11: Oflox-200 Tab | C11: Anti-microbial | D11: 5 | E11: Ram Agencies | F11: 45931 | G11: 69.581818 | H11: 76.54 | I11: 350.8 | J11: =H11-G11 -> 6.9581818 | K11: =J11*D11 -> 34.790909
A12: 11 | B12: Ketafung CT Solution | C12: Body Care | D12: 1 | E12: Ram Agencies | F12: 45931 | G12: 218.67273 | H12: 240.54 | I12: 244.98 | J12: =H12-G12 -> 21.867273 | K12: =J12*D12 -> 21.867273
A13: 12 | B13: Strepsils Orange | C13: Cold/Cough | D13: 1 | E13: Ram Agencies | F13: 45931 | G13: 572.72727 | H13: 630 | I13: 661.5 | J13: =H13-G13 -> 57.272727 | K13: =J13*D13 -> 57.272727
... A583: 584 | B583: Nebicard T Tab | C583: Cardiovascular | D583: 1 | E583: RSM Pharma | F583: 45960 | G583: 232.40909 | H583: 255.65 | I583: 260.38 | J583: =H583-G583 -> 23.240909 | K583: =J583*D583 -> 23.240909

Sheet Cleaned data Expiry
A1: Serial No. | B1: Item Description | C1: Category | D1: Quantity | E1: Expiry Date | F1: MRP | G1: Total
A2: 1 | B2: Lecmon-AM | C2: Anti-microbial | D2: 15 | E2: 45901 | F2: 169 | G2: =F2*D2 -> 2535
A3: 2 | B3: Proanagen Tabs | C3: Skincare | D3: 5 | E3: 45962 | F3: 263 | G3: =F3*D3 -> 1315
A4: 3 | B4: Xaliderm Solution | C4: Immunosuppresant | D4: 35 | E4: 45962 | F4: 299 | G4: =F4*D4 -> 10465
A5: 4 | B5: Everolimus | C5: Immunosuppresant | D5: 25 | E5: 45992 | F5: 191.66 | G5: =F5*D5 -> 4791.5
A6: 5 | B6: Prednisone | C6: Immunosuppresant | D6: 15 | E6: 45962 | F6: 70.56 | G6: =F6*D6 -> 1058.4
A7: 6 | B7: Terbinaforce 500 | C7: Anti-microbial | D7: 10 | E7: 45839 | F7: 184.47 | G7: =F7*D7 -> 1844.7
A8: 7 | B8: Methylprednisolone | C8: Immunosuppresant | D8: 15 | E8: 45992 | F8: 143.37 | G8: =F8*D8 -> 2150.55
A9: 8 | B9: Ocid 20 | C9: Gastro Tabs | D9: 10 | E9: 45901 | F9: 64.28 | G9: =F9*D9 -> 642.8 | K9: Total cost of expired products | L9: =SUM(G2:G46) -> 97457.38
A10: 9 | B10: Tacrolimus | C10: Immunosuppresant | D10: 8 | E10: 46023 | F10: 249 | G10: =F10*D10 -> 1992 | K10: Total revenue | L10: 424224.86
A11: 10 | B11: Metsmall 500 | C11: Immunosuppresant | D11: 9 | E11: 45962 | F11: 54 | G11: =F11*D11 -> 486 | K11: Percentage of Loss due to expired products | L11: =L9/L10 -> 0.22973048
A12: 11 | B12: Cyclosporine | C12: Immunosuppresant | D12: 20 | E12: 45992 | F12: 32.04 | G12: =F12*D12 -> 640.8
A13: 12 | B13: Infliximab | C13: Immunosuppresant | D13: 9 | E13: 45809 | F13: 64.96 | G13: =F13*D13 -> 584.64
A14: 13 | B14: Sinarest | C14: Cold/Cough | D14: 15 | E14: 45901 | F14: 133.75 | G14: =F14*D14 -> 2006.25
A15: 14 | B15: Alembic | C15: Skincare | D15: 5 | E15: 45962 | F15: 726 | G15: =F15*D15 -> 3630
A16: 15 | B16: ItchInsta | C16: Skincare | D16: 5 | E16: 45962 | F16: 305 | G16: =F16*D16 -> 1525
A17: 16 | B17: Suncros | C17: Sunscreen | D17: 8 | E17: 42217 | F17: 850 | G17: =F17*D17 -> 6800
A18: 17 | B18: Itrazet-200 | C18: Pain Relief | D18: 10 | E18: 45992 | F18: 247.5 | G18: =F18*D18 -> 2475
A19: 18 | B19: Mycophenolate Mofetil | C19: Immunosuppresant | D19: 20 | E19: 46023 | F19: 108.05 | G19: =F19*D19 -> 2161
A20: 19 | B20: Laveta M | C20: Pain Relief | D20: 9 | E20: 45992 | F20: 221.35 | G20: =F20*D20 -> 1992.15
A21: 20 | B21: Azathioprine | C21: Immunosuppresant | D21: 14 | E21: 45962 | F21: 443.76 | G21: =F21*D21 -> 6212.64
A22: 21 | B22: Inclofax | C22: Pain Relief | D22: 10 | E22: 45839 | F22: 52 | G22: =F22*D22 -> 520
A23: 22 | B23: Dailycal-500 | C23: Vitamins/Minerals | D23: 7 | E23: 45962 | F23: 60 | G23: =F23*D23 -> 420
... A46: 45 | B46: Tenolol 50MG | C46: Cardiovascular | D46: 20 | E46: 45901 | F46: 35 | G46: =F46*D46 -> 700

Sheet Analysis I
G2: A/B/C Analysis
B3: Row Labels | C3: Sum of Net Value | D3: Sum of Quantity | G3: Row Labels | H3: Sum of Net Value | I3: Percentage | J3: Cummulative Sum | K3: Cummulate Percentage | L3: A/B/C
B4: Skincare | C4: 130075.75 | D4: 341 | G4: Skincare | H4: 130075.75 | I4: =H4/H$19 -> 0.30661982 | J4: =H4 -> 130075.75 | K4: =I4 -> 0.30661982 | L4: A | O4: F(Fast Moving Items) | P4: S(Slow Moving Items) | Q4: N(Non-Moving items)
B5: Anti-microbial | C5: 87656.09 | D5: 621 | G5: Anti-microbial | H5: 87656.09 | I5: =H5/H$19 -> 0.20662648 | J5: =J4+H5 -> 217731.84 | K5: =(J5/J$17) -> 0.5132463 | L5: A | N5: CLASS A | O5: =1+1+1+1 -> 4 | P5: =1 -> 1 | Q5: 0
B6: Body Care | C6: 68741.59 | D6: 184 | G6: Body Care | H6: 68741.59 | I6: =H6/H$19 -> 0.16204046 | J6: =J5+H6 -> 286473.43 | K6: =(J6/J$17) -> 0.67528676 | L6: A | N6: CLASS B | O6: 1 | P6: 2 | Q6: 1
B7: Vitamins/Minerals | C7: 27297.65 | D7: 255 | G7: Vitamins/Minerals | H7: 27297.65 | I7: =H7/H$19 -> 0.064347125 | J7: =J6+H7 -> 313771.08 | K7: =(J7/J$17) -> 0.73963388 | L7: A | N7: CLASS C | O7: 0 | P7: =1 -> 1 | Q7: 4
B8: Pain Relief | C8: 25688.45 | D8: 265 | G8: Pain Relief | H8: 25688.45 | I8: =H8/H$19 -> 0.060553853 | J8: =J7+H8 -> 339459.53 | K8: =(J8/J$17) -> 0.80018774 | L8: A
B9: Cardiovascular | C9: 20768.13 | D9: 190 | G9: Cardiovascular | H9: 20768.13 | I9: =H9/H$19 -> 0.048955476 | J9: =J8+H9 -> 360227.66 | K9: =(J9/J$17) -> 0.84914321 | L9: B
B10: Sunscreen | C10: 13624.1 | D10: 21 | G10: Sunscreen | H10: 13624.1 | I10: =H10/H$19 -> 0.03211528 | J10: =J9+H10 -> 373851.76 | K10: =(J10/J$17) -> 0.88125849 | L10: B
B11: Diabetes | C11: 12331.55 | D11: 91 | G11: Diabetes | H11: 12331.55 | I11: =H11/H$19 -> 0.029068428 | J11: =J10+H11 -> 386183.31 | K11: =(J11/J$17) -> 0.91032692 | L11: B
B12: Gastro Tabs | C12: 11714.39 | D12: 119 | G12: Gastro Tabs | H12: 11714.39 | I12: =H12/H$19 -> 0.027613634 | J12: =J11+H12 -> 397897.7 | K12: =(J12/J$17) -> 0.93794055 | L12: B
B13: Respiratory | C13: 11057.12 | D13: 111 | G13: Respiratory | H13: 11057.12 | I13: =H13/H$19 -> 0.026064291 | J13: =J12+H13 -> 408954.82 | K13: =(J13/J$17) -> 0.96400484 | L13: C
B14: Cold/Cough | C14: 7530.95 | D14: 53 | G14: Cold/Cough | H14: 7530.95 | I14: =H14/H$19 -> 0.01775226 | J14: =J13+H14 -> 416485.77 | K14: =(J14/J$17) -> 0.9817571 | L14: C
B15: First Aid | C15: 3158.16 | D15: 23 | G15: First Aid | H15: 3158.16 | I15: =H15/H$19 -> 0.0074445425 | J15: =J14+H15 -> 419643.93 | K15: =(J15/J$17) -> 0.98920165 | L15: C
B16: Baby Care | C16: 2858.11 | D16: 13 | G16: Baby Care | H16: 2858.11 | I16: =H16/H$19 -> 0.0067372525 | J16: =J15+H16 -> 422502.04 | K16: =(J16/J$17) -> 0.9959389 | L16: C
B17: Immunosuppressant | C17: 1722.82 | D17: 15 | G17: Immunosuppressant | H17: 1722.82 | I17: =H17/H$19 -> 0.004061101 | J17: =J16+H17 -> 424224.86 | K17: =(J17/J$17) -> 1 | L17: C
B18: (blank)
B19: Grand Total | C19: 424224.86 | D19: 2302 | G19: Total Revenue | H19: 424224.86
K20: A(Top 80%) | L20: 80+15
K21: B(Next 15%) | L21: 95+5
K22: C(Botton 5%)
G24: FSN Analysis
G25: Row Labels | H25: Sum of Quantity | I25: Percentage(Items) | J25: Cummulative Sum(Items) | K25: Cummulative %(Items) | L25: FSN
G26: Anti-microbial | H26: 621 | I26: =H26/H$41 -> 0.26976542 | J26: =H26 -> 621 | K26: =I26 -> 0.26976542 | L26: F
B27: PARETO PRINCIPLE | G27: Skincare | H27: 341 | I27: =H27/H$41 -> 0.14813206 | J27: =J26+H27 -> 962 | K27: =J27/J$39 -> 0.41789748 | L27: F
B28: 20% of the products | C28: =0.2*14 -> 2.8 | D28: Categories | G28: Pain Relief | H28: 265 | I28: =H28/H$41 -> 0.11511729 | J28: =J27+H28 -> 1227 | K28: =J28/J$39 -> 0.53301477 | L28: F
B29: 80% of Revenue? | C29: 0.675 | G29: Vitamins/Minerals | H29: 255 | I29: =H29/H$41 -> 0.11077324 | J29: =J28+H29 -> 1482 | K29: =J29/J$39 -> 0.64378801 | L29: F
B30: Not applicable | G30: Cardiovascular | H30: 190 | I30: =H30/H$41 -> 0.082536924 | J30: =J29+H30 -> 1672 | K30: =J30/J$39 -> 0.72632493 | L30: F | N30: F(Fast Moving Items Top 80%)
G31: Body Care | H31: 184 | I31: =H31/H$41 -> 0.079930495 | J31: =J30+H31 -> 1856 | K31: =J31/J$39 -> 0.80625543 | L31: S | N31: S(Slow Moving Items 15%)
G32: Gastro Tabs | H32: 119 | I32: =H32/H$41 -> 0.051694179 | J32: =J31+H32 -> 1975 | K32: =J32/J$39 -> 0.85794961 | L32: S | N32: N(Non Moving Items Bottom 5%)
G33: Respiratory | H33: 111 | I33: =H33/H$41 -> 0.04821894 | J33: =J32+H33 -> 2086 | K33: =J33/J$39 -> 0.90616855 | L33: S
G34: Diabetes | H34: 91 | I34: =H34/H$41 -> 0.039530843 | J34: =J33+H34 -> 2177 | K34: =J34/J$39 -> 0.94569939 | L34: S
G35: Cold/Cough | H35: 53 | I35: =H35/H$41 -> 0.023023458 | J35: =J34+H35 -> 2230 | K35: =J35/J$39 -> 0.96872285 | L35: N
G36: First Aid | H36: 23 | I36: =H36/H$41 -> 0.0099913119 | J36: =J35+H36 -> 2253 | K36: =J36/J$39 -> 0.97871416 | L36: N
G37: Sunscreen | H37: 21 | I37: =H37/H$41 -> 0.0091225022 | J37: =J36+H37 -> 2274 | K37: =J37/J$39 -> 0.98783666 | L37: N
G38: Immunosuppressant | H38: 15 | I38: =H38/H$41 -> 0.006516073 | J38: =J37+H38 -> 2289 | K38: =J38/J$39 -> 0.99435274 | L38: N
G39: Baby Care | H39: 13 | I39: =H39/H$41 -> 0.0056472632 | J39: =J38+H39 -> 2302 | K39: =J39/J$39 -> 1 | L39: N
G41: Total Quantity | H41: 2302 | P41: Expired Data Analysis
J42: F (Fast Selling ) | K42: =H26+H27+H28+H29+H30 -> 1672 | L42: =K42/K$45 -> 0.72632493 | P42: Row Labels | Q42: Sum of Total | R42: Percentage of Loss
J43: S (Slow Selling ) | K43: =SUM(H31:H34) -> 505 | L43: =K43/K$45 -> 0.21937446 | P43: Anti-microbial | Q43: 4379.7 | R43: =Q43/Q$53 -> 0.044939644
J44: N (Non Moving) | K44: =SUM(H35:H39) -> 125 | L44: =K44/K$45 -> 0.054300608 | P44: Cardiovascular | Q44: 7096.3 | R44: =Q44/Q$53 -> 0.072814393
K45: =SUM(K42:K44) -> 2302 | P45: Cold/Cough | Q45: 2006.25 | R45: =Q45/Q$53 -> 0.020585922
P46: Diabetes | Q46: 7284 | R46: =Q46/Q$53 -> 0.074740363
P47: Pain Relief | Q47: 11063.17 | R47: =Q47/Q$53 -> 0.11351803
P48: Skincare | Q48: 11404.88 | R48: =Q48/Q$53 -> 0.11702428
P49: Sunscreen | Q49: 6800 | R49: =Q49/Q$53 -> 0.06977409
P50: Vitamins/Minerals | Q50: 4800 | R50: =Q50/Q$53 -> 0.049252299
P51: Immunosuppresant | Q51: 41434.28 | R51: =Q51/Q$53 -> 0.42515282
P52: Gastro Tabs | Q52: 1188.8 | R52: =Q52/Q$53 -> 0.012198153
P53: Grand Total | Q53: 97457.38

Sheet Analysis II
A2: EOQ(Economic order quantity for a category) | B2: sqrt((2DS)/H) | M2: Combined ABC, FSN, EOQ and ROP Analysis Table
A3: D(total units of category sold in a month x12) | M3: Row Labels | N3: A/B/C | O3: FSN | P3: EOQ | Q3: ROP
A4: S (Micellaneous cost ) | B4: 200 | D4: Row Labels | E4: Sum of Quantity | F4: Sum of Selling Price | G4: Avg Unit Cost for each category | H4: Holding Cost(H) | I4: Demand(D) | J4: EOQ | M4: Skincare | N4: A | O4: F | P4: =_xlfn.XLOOKUP(M4,'Analysis II'!$D$5:$D$18,'Analysis II'!J$5:J$18,0) -> 272.94484 | Q4: 114
A5: H(Holding cost) | B5: 20% of unit cost | D5: Anti-microbial | E5: 621 | F5: 20776.51 | G5: =F5/E5 -> 33.456538 | H5: =0.2*G5 -> 6.6913076 | I5: =E5*12 -> 7452 | J5: =SQRT((2*I5*B$4)/H5) -> 667.43799 | M5: Anti-microbial | N5: A | O5: F | P5: =_xlfn.XLOOKUP(M5,'Analysis II'!$D$5:$D$18,'Analysis II'!J$5:J$18,0) -> 667.43799 | Q5: 207
D6: Baby Care | E6: 13 | F6: 1952.04 | G6: =F6/E6 -> 150.15692 | H6: =0.2*G6 -> 30.031385 | I6: =E6*12 -> 156 | J6: =SQRT((2*I6*B$4)/H6) -> 45.58318 | M6: Body Care | N6: A | O6: S | P6: =_xlfn.XLOOKUP(M6,'Analysis II'!$D$5:$D$18,'Analysis II'!J$5:J$18,0) -> 182.01102 | Q6: 61
D7: Body Care | E7: 184 | F7: 24527.4 | G7: =F7/E7 -> 133.30109 | H7: =0.2*G7 -> 26.660217 | I7: =E7*12 -> 2208 | J7: =SQRT((2*I7*B$4)/H7) -> 182.01102 | M7: Vitamins/Minerals | N7: A | O7: F | P7: =_xlfn.XLOOKUP(M7,'Analysis II'!$D$5:$D$18,'Analysis II'!J$5:J$18,0) -> 426.40044 | Q7: 85
D8: Cardiovascular | E8: 190 | F8: 6550.63 | G8: =F8/E8 -> 34.477 | H8: =0.2*G8 -> 6.8954 | I8: =E8*12 -> 2280 | J8: =SQRT((2*I8*B$4)/H8) -> 363.67855 | M8: Pain Relief | N8: A | O8: F | P8: =_xlfn.XLOOKUP(M8,'Analysis II'!$D$5:$D$18,'Analysis II'!J$5:J$18,0) -> 506.45791 | Q8: 88
D9: Cold/Cough | E9: 53 | F9: 5241.41 | G9: =F9/E9 -> 98.894528 | H9: =0.2*G9 -> 19.778906 | I9: =E9*12 -> 636 | J9: =SQRT((2*I9*B$4)/H9) -> 113.41159 | M9: Cardiovascular | N9: B | O9: F | P9: =_xlfn.XLOOKUP(M9,'Analysis II'!$D$5:$D$18,'Analysis II'!J$5:J$18,0) -> 363.67855 | Q9: 63
D10: Diabetes | E10: 91 | F10: 4247.17 | G10: =F10/E10 -> 46.672198 | H10: =0.2*G10 -> 9.3344396 | I10: =E10*12 -> 1092 | J10: =SQRT((2*I10*B$4)/H10) -> 216.32026 | M10: Sunscreen | N10: B | O10: N | P10: =_xlfn.XLOOKUP(M10,'Analysis II'!$D$5:$D$18,'Analysis II'!J$5:J$18,0) -> 36.351104 | Q10: 7
D11: First Aid | E11: 23 | F11: 1963.2 | G11: =F11/E11 -> 85.356522 | H11: =0.2*G11 -> 17.071304 | I11: =E11*12 -> 276 | J11: =SQRT((2*I11*B$4)/H11) -> 80.417614 | M11: Diabetes | N11: B | O11: S | P11: =_xlfn.XLOOKUP(M11,'Analysis II'!$D$5:$D$18,'Analysis II'!J$5:J$18,0) -> 216.32026 | Q11: 30
D12: Gastro Tabs | E12: 119 | F12: 4847.59 | G12: =F12/E12 -> 40.73605 | H12: =0.2*G12 -> 8.1472101 | I12: =E12*12 -> 1428 | J12: =SQRT((2*I12*B$4)/H12) -> 264.78272 | M12: Gastro Tabs | N12: B | O12: S | P12: =_xlfn.XLOOKUP(M12,'Analysis II'!$D$5:$D$18,'Analysis II'!J$5:J$18,0) -> 264.78272 | Q12: 40
D13: Immunosuppressant | E13: 15 | F13: 841.15 | G13: =F13/E13 -> 56.076667 | H13: =0.2*G13 -> 11.215333 | I13: =E13*12 -> 180 | J13: =SQRT((2*I13*B$4)/H13) -> 80.123545 | M13: Respiratory | N13: C | O13: S | P13: =_xlfn.XLOOKUP(M13,'Analysis II'!$D$5:$D$18,'Analysis II'!J$5:J$18,0) -> 218.7546 | Q13: 37
D14: Pain Relief | E14: 265 | F14: 6570.77 | G14: =F14/E14 -> 24.795358 | H14: =0.2*G14 -> 4.9590717 | I14: =E14*12 -> 3180 | J14: =SQRT((2*I14*B$4)/H14) -> 506.45791 | M14: Cold/Cough | N14: C | O14: N | P14: =_xlfn.XLOOKUP(M14,'Analysis II'!$D$5:$D$18,'Analysis II'!J$5:J$18,0) -> 113.41159 | Q14: 18
D15: Respiratory | E15: 111 | F15: 6179.35 | G15: =F15/E15 -> 55.66982 | H15: =0.2*G15 -> 11.133964 | I15: =E15*12 -> 1332 | J15: =SQRT((2*I15*B$4)/H15) -> 218.7546 | M15: First Aid | N15: C | O15: N | P15: =_xlfn.XLOOKUP(M15,'Analysis II'!$D$5:$D$18,'Analysis II'!J$5:J$18,0) -> 80.417614 | Q15: 8
D16: Skincare | E16: 341 | F16: 37460.21 | G16: =F16/E16 -> 109.85399 | H16: =0.2*G16 -> 21.970798 | I16: =E16*12 -> 4092 | J16: =SQRT((2*I16*B$4)/H16) -> 272.94484 | M16: Baby Care | N16: C | O16: N | P16: =_xlfn.XLOOKUP(M16,'Analysis II'!$D$5:$D$18,'Analysis II'!J$5:J$18,0) -> 45.58318 | Q16: 4
D17: Sunscreen | E17: 21 | F17: 8009.67 | G17: =F17/E17 -> 381.41286 | H17: =0.2*G17 -> 76.282571 | I17: =E17*12 -> 252 | J17: =SQRT((2*I17*B$4)/H17) -> 36.351104 | M17: Immunosuppressant | N17: C | O17: N | P17: =_xlfn.XLOOKUP(M17,'Analysis II'!$D$5:$D$18,'Analysis II'!J$5:J$18,0) -> 80.123545 | Q17: 5
D18: Vitamins/Minerals | E18: 255 | F18: 8583.34 | G18: =F18/E18 -> 33.660157 | H18: =0.2*G18 -> 6.7320314 | I18: =E18*12 -> 3060 | J18: =SQRT((2*I18*B$4)/H18) -> 426.40044
D19: Grand Total | E19: 2302 | F19: 137750.44
A22: ROP (Reorder Point ) | B22: ( d*LL)+ s | D22: Row Labels | E22: Sum of Quantity | F22: Daily Demand | G22: Safety Stock | H22: ROP
A23: d | B23: Daily Demand | D23: Anti-microbial | E23: 621 | F23: =E23/30 -> 20.7 | G23: =0.2*E23 -> 124.2 | H23: =(F23*B$24)+G23 -> 207
A24: LL | B24: 4 | C24: days | D24: Baby Care | E24: 13 | F24: =E24/30 -> 0.43333333 | G24: =0.2*E24 -> 2.6 | H24: =(F24*B$24)+G24 -> 4.3333333
A25: s | B25: 20% of monthly demand | D25: Body Care | E25: 184 | F25: =E25/30 -> 6.1333333 | G25: =0.2*E25 -> 36.8 | H25: =(F25*B$24)+G25 -> 61.333333
D26: Cardiovascular | E26: 190 | F26: =E26/30 -> 6.3333333 | G26: =0.2*E26 -> 38 | H26: =(F26*B$24)+G26 -> 63.333333
D27: Cold/Cough | E27: 53 | F27: =E27/30 -> 1.7666667 | G27: =0.2*E27 -> 10.6 | H27: =(F27*B$24)+G27 -> 17.666667
D28: Diabetes | E28: 91 | F28: =E28/30 -> 3.0333333 | G28: =0.2*E28 -> 18.2 | H28: =(F28*B$24)+G28 -> 30.333333
D29: First Aid | E29: 23 | F29: =E29/30 -> 0.76666667 | G29: =0.2*E29 -> 4.6 | H29: =(F29*B$24)+G29 -> 7.6666667
D30: Gastro Tabs | E30: 119 | F30: =E30/30 -> 3.9666667 | G30: =0.2*E30 -> 23.8 | H30: 40
D31: Immunosuppressant | E31: 15 | F31: =E31/30 -> 0.5 | G31: =0.2*E31 -> 3 | H31: =(F31*B$24)+G31 -> 5
D32: Pain Relief | E32: 265 | F32: =E32/30 -> 8.8333333 | G32: =0.2*E32 -> 53 | H32: =(F32*B$24)+G32 -> 88.333333
D33: Respiratory | E33: 111 | F33: =E33/30 -> 3.7 | G33: =0.2*E33 -> 22.2 | H33: =(F33*B$24)+G33 -> 37
D34: Skincare | E34: 341 | F34: =E34/30 -> 11.366667 | G34: =0.2*E34 -> 68.2 | H34: =(F34*B$24)+G34 -> 113.66667
D35: Sunscreen | E35: 21 | F35: =E35/30 -> 0.7 | G35: =0.2*E35 -> 4.2 | H35: =(F35*B$24)+G35 -> 7
D36: Vitamins/Minerals | E36: 255 | F36: =E36/30 -> 8.5 | G36: =0.2*E36 -> 51 | H36: =(F36*B$24)+G36 -> 85
D37: Grand Total | E37: 2302

Sheet Analysis III
AF1: Inventory Risk Heat Map
X2: Category | Y2: Average Daily Demand | Z2: Coefficient of Variation (CV) | AF2: Category | AG2: Expiry Risk | AH2: Demand Stability | AI2: Revenue Importance
B3: Category | C3: ABC | D3: FSN | E3: EOQ Applicability | F3: Recommended Inventory Action | H3: Category | I3: Daily Demand (Average) | J3: Safety Stock | K3: ROP | X3: Anti-microbial | Y3: 20.7 | Z3: 1.475369 | AF3: Anti-microbial | AG3: 1 | AH3: 2 | AI3: 3
B4: Anti-microbial | C4: =_xlfn.XLOOKUP(B4,'Analysis II'!M$4:M$17,'Analysis II'!N$4:N$17,0) -> A | D4: =_xlfn.XLOOKUP(B4,'Analysis II'!M$4:M$17,'Analysis II'!O$4:O$17,0) -> F | E4: High | F4: EOQ-based ordering | H4: Anti-microbial | I4: =_xlfn.XLOOKUP(H4,'Analysis II'!D$23:D$36,'Analysis II'!F$23:F$36,0) -> 20.7 | J4: =_xlfn.XLOOKUP(H4,'Analysis II'!D$23:D$36,'Analysis II'!G$23:G$36,0) -> 124.2 | K4: =_xlfn.XLOOKUP(H4,'Analysis II'!D23:D36,'Analysis II'!H23:H36,0) -> 207 | X4: Skincare | Y4: 11.366667 | Z4: 0.95914975 | AB4: 3 = High expiry loss | AF4: Baby Care | AG4: 1 | AH4: 3 | AI4: 1
B5: Baby Care | C5: =_xlfn.XLOOKUP(B5,'Analysis II'!M$4:M$17,'Analysis II'!N$4:N$17,0) -> C | D5: =_xlfn.XLOOKUP(B5,'Analysis II'!M$4:M$17,'Analysis II'!O$4:O$17,0) -> N | E5: Low | F5: Minimal Stock / Demand Based | H5: Baby Care | I5: =_xlfn.XLOOKUP(H5,'Analysis II'!D$23:D$36,'Analysis II'!F$23:F$36,0) -> 0.43333333 | J5: =_xlfn.XLOOKUP(H5,'Analysis II'!D$23:D$36,'Analysis II'!G$23:G$36,0) -> 2.6 | K5: =_xlfn.XLOOKUP(H5,'Analysis II'!D24:D37,'Analysis II'!H24:H37,0) -> 4.3333333 | X5: Pain Relief | Y5: 8.8333333 | Z5: 1.2828945 | AB5: 2 = Moderate expiry risk | AF5: Body Care | AG5: 1 | AH5: 2 | AI5: 3
B6: Body Care | C6: =_xlfn.XLOOKUP(B6,'Analysis II'!M$4:M$17,'Analysis II'!N$4:N$17,0) -> A | D6: =_xlfn.XLOOKUP(B6,'Analysis II'!M$4:M$17,'Analysis II'!O$4:O$17,0) -> S | E6: Medium | F6: EOQ with periodic review | H6: Body Care | I6: =_xlfn.XLOOKUP(H6,'Analysis II'!D$23:D$36,'Analysis II'!F$23:F$36,0) -> 6.1333333 | J6: =_xlfn.XLOOKUP(H6,'Analysis II'!D$23:D$36,'Analysis II'!G$23:G$36,0) -> 36.8 | K6: =_xlfn.XLOOKUP(H6,'Analysis II'!D25:D38,'Analysis II'!H25:H38,0) -> 61.333333 | X6: Vitamins/Minerals | Y6: 8.5 | Z6: 1.1099876 | AB6: 1 = Low or negligible expiry | AF6: Cardiovascular | AG6: 2 | AH6: 2 | AI6: 2
B7: Cardiovascular | C7: =_xlfn.XLOOKUP(B7,'Analysis II'!M$4:M$17,'Analysis II'!N$4:N$17,0) -> B | D7: =_xlfn.XLOOKUP(B7,'Analysis II'!M$4:M$17,'Analysis II'!O$4:O$17,0) -> F | E7: High | F7: EOQ-based ordering | H7: Cardiovascular | I7: =_xlfn.XLOOKUP(H7,'Analysis II'!D$23:D$36,'Analysis II'!F$23:F$36,0) -> 6.3333333 | J7: =_xlfn.XLOOKUP(H7,'Analysis II'!D$23:D$36,'Analysis II'!G$23:G$36,0) -> 38 | K7: =_xlfn.XLOOKUP(H7,'Analysis II'!D26:D39,'Analysis II'!H26:H39,0) -> 63.333333 | X7: Cardiovascular | Y7: 6.3333333 | Z7: 1.2176465 | AF7: Cold/Cough | AG7: 1 | AH7: 3 | AI7: 1
B8: Cold/Cough | C8: =_xlfn.XLOOKUP(B8,'Analysis II'!M$4:M$17,'Analysis II'!N$4:N$17,0) -> C | D8: =_xlfn.XLOOKUP(B8,'Analysis II'!M$4:M$17,'Analysis II'!O$4:O$17,0) -> N | E8: Low | F8: Minimal Stock / Demand Based | H8: Cold/Cough | I8: =_xlfn.XLOOKUP(H8,'Analysis II'!D$23:D$36,'Analysis II'!F$23:F$36,0) -> 1.7666667 | J8: =_xlfn.XLOOKUP(H8,'Analysis II'!D$23:D$36,'Analysis II'!G$23:G$36,0) -> 10.6 | K8: =_xlfn.XLOOKUP(H8,'Analysis II'!D27:D40,'Analysis II'!H27:H40,0) -> 17.666667 | X8: Body Care | Y8: 6.1333333 | Z8: 1.2009729 | AB8: CV > 2.0 : Highly unstable :3 | AF8: Diabetes | AG8: 2 | AH8: 2 | AI8: 2
B9: Diabetes | C9: =_xlfn.XLOOKUP(B9,'Analysis II'!M$4:M$17,'Analysis II'!N$4:N$17,0) -> B | D9: =_xlfn.XLOOKUP(B9,'Analysis II'!M$4:M$17,'Analysis II'!O$4:O$17,0) -> S | E9: Medium | F9: EOQ with periodic review | H9: Diabetes | I9: =_xlfn.XLOOKUP(H9,'Analysis II'!D$23:D$36,'Analysis II'!F$23:F$36,0) -> 3.0333333 | J9: =_xlfn.XLOOKUP(H9,'Analysis II'!D$23:D$36,'Analysis II'!G$23:G$36,0) -> 18.2 | K9: =_xlfn.XLOOKUP(H9,'Analysis II'!D28:D41,'Analysis II'!H28:H41,0) -> 30.333333 | X9: Gastro Tabs | Y9: 3.9666667 | Z9: 1.917068 | AB9: 1.2 ≤ CV ≤ 2.0 : Moderately unstable : 2 | AF9: First Aid | AG9: 1 | AH9: 3 | AI9: 1
B10: First Aid | C10: =_xlfn.XLOOKUP(B10,'Analysis II'!M$4:M$17,'Analysis II'!N$4:N$17,0) -> C | D10: =_xlfn.XLOOKUP(B10,'Analysis II'!M$4:M$17,'Analysis II'!O$4:O$17,0) -> N | E10: Low | F10: Minimal Stock / Demand Based | H10: First Aid | I10: =_xlfn.XLOOKUP(H10,'Analysis II'!D$23:D$36,'Analysis II'!F$23:F$36,0) -> 0.76666667 | J10: =_xlfn.XLOOKUP(H10,'Analysis II'!D$23:D$36,'Analysis II'!G$23:G$36,0) -> 4.6 | K10: =_xlfn.XLOOKUP(H10,'Analysis II'!D29:D42,'Analysis II'!H29:H42,0) -> 7.6666667 | X10: Respiratory | Y10: 3.7 | Z10: 2.4341404 | AB10: CV < 1.2 : Stable : 1 | AF10: Gastro Tabs | AG10: 1 | AH10: 2 | AI10: 2
B11: Gastro Tabs | C11: =_xlfn.XLOOKUP(B11,'Analysis II'!M$4:M$17,'Analysis II'!N$4:N$17,0) -> B | D11: =_xlfn.XLOOKUP(B11,'Analysis II'!M$4:M$17,'Analysis II'!O$4:O$17,0) -> S | E11: Medium | F11: EOQ with periodic review | H11: Gastro Tabs | I11: =_xlfn.XLOOKUP(H11,'Analysis II'!D$23:D$36,'Analysis II'!F$23:F$36,0) -> 3.9666667 | J11: =_xlfn.XLOOKUP(H11,'Analysis II'!D$23:D$36,'Analysis II'!G$23:G$36,0) -> 23.8 | K11: =_xlfn.XLOOKUP(H11,'Analysis II'!D30:D43,'Analysis II'!H30:H43,0) -> 40 | X11: Diabetes | Y11: 3.0333333 | Z11: 1.4907197 | AF11: Immunosuppressant | AG11: 3 | AH11: 3 | AI11: 1 | AK11: Low
B12: Immunosuppressant | C12: =_xlfn.XLOOKUP(B12,'Analysis II'!M$4:M$17,'Analysis II'!N$4:N$17,0) -> C | D12: =_xlfn.XLOOKUP(B12,'Analysis II'!M$4:M$17,'Analysis II'!O$4:O$17,0) -> N | E12: Low | F12: Minimal Stock / Demand Based | H12: Immunosuppressant | I12: =_xlfn.XLOOKUP(H12,'Analysis II'!D$23:D$36,'Analysis II'!F$23:F$36,0) -> 0.5 | J12: =_xlfn.XLOOKUP(H12,'Analysis II'!D$23:D$36,'Analysis II'!G$23:G$36,0) -> 3 | K12: =_xlfn.XLOOKUP(H12,'Analysis II'!D31:D44,'Analysis II'!H31:H44,0) -> 5 | X12: Cold/Cough | Y12: 1.7666667 | Z12: 2.3109191 | AB12: A:3 | AF12: Pain Relief | AG12: 3 | AH12: 2 | AI12: 3 | AK12: Moderate
B13: Pain Relief | C13: =_xlfn.XLOOKUP(B13,'Analysis II'!M$4:M$17,'Analysis II'!N$4:N$17,0) -> A | D13: =_xlfn.XLOOKUP(B13,'Analysis II'!M$4:M$17,'Analysis II'!O$4:O$17,0) -> F | E13: High | F13: EOQ-based ordering | H13: Pain Relief | I13: =_xlfn.XLOOKUP(H13,'Analysis II'!D$23:D$36,'Analysis II'!F$23:F$36,0) -> 8.8333333 | J13: =_xlfn.XLOOKUP(H13,'Analysis II'!D$23:D$36,'Analysis II'!G$23:G$36,0) -> 53 | K13: =_xlfn.XLOOKUP(H13,'Analysis II'!D32:D45,'Analysis II'!H32:H45,0) -> 88.333333 | X13: First Aid | Y13: 0.76666667 | Z13: 2.1027327 | AB13: B:2 | AF13: Respiratory | AG13: 1 | AH13: 3 | AI13: 1 | AK13: High
B14: Respiratory | C14: =_xlfn.XLOOKUP(B14,'Analysis II'!M$4:M$17,'Analysis II'!N$4:N$17,0) -> C | D14: =_xlfn.XLOOKUP(B14,'Analysis II'!M$4:M$17,'Analysis II'!O$4:O$17,0) -> S | E14: Low | F14: Minimal Stock / Demand Based | H14: Respiratory | I14: =_xlfn.XLOOKUP(H14,'Analysis II'!D$23:D$36,'Analysis II'!F$23:F$36,0) -> 3.7 | J14: =_xlfn.XLOOKUP(H14,'Analysis II'!D$23:D$36,'Analysis II'!G$23:G$36,0) -> 22.2 | K14: =_xlfn.XLOOKUP(H14,'Analysis II'!D33:D46,'Analysis II'!H33:H46,0) -> 37 | X14: Sunscreen | Y14: 0.7 | Z14: 1.7656508 | AB14: C:1 | AF14: Skincare | AG14: 3 | AH14: 1 | AI14: 3
B15: Skincare | C15: =_xlfn.XLOOKUP(B15,'Analysis II'!M$4:M$17,'Analysis II'!N$4:N$17,0) -> A | D15: =_xlfn.XLOOKUP(B15,'Analysis II'!M$4:M$17,'Analysis II'!O$4:O$17,0) -> F | E15: High | F15: EOQ-based ordering | H15: Skincare | I15: =_xlfn.XLOOKUP(H15,'Analysis II'!D$23:D$36,'Analysis II'!F$23:F$36,0) -> 11.366667 | J15: =_xlfn.XLOOKUP(H15,'Analysis II'!D$23:D$36,'Analysis II'!G$23:G$36,0) -> 68.2 | K15: =_xlfn.XLOOKUP(H15,'Analysis II'!D34:D47,'Analysis II'!H34:H47,0) -> 113.66667 | X15: Immunosuppressant | Y15: 0.5 | Z15: 4.4178322 | AF15: Sunscreen | AG15: 2 | AH15: 2 | AI15: 2
B16: Sunscreen | C16: =_xlfn.XLOOKUP(B16,'Analysis II'!M$4:M$17,'Analysis II'!N$4:N$17,0) -> B | D16: =_xlfn.XLOOKUP(B16,'Analysis II'!M$4:M$17,'Analysis II'!O$4:O$17,0) -> N | E16: Low | F16: Minimal Stock / Demand Based | H16: Sunscreen | I16: =_xlfn.XLOOKUP(H16,'Analysis II'!D$23:D$36,'Analysis II'!F$23:F$36,0) -> 0.7 | J16: =_xlfn.XLOOKUP(H16,'Analysis II'!D$23:D$36,'Analysis II'!G$23:G$36,0) -> 4.2 | K16: =_xlfn.XLOOKUP(H16,'Analysis II'!D35:D48,'Analysis II'!H35:H48,0) -> 7 | X16: Baby Care | Y16: 0.43333333 | Z16: 2.4753426 | AF16: Vitamins/Minerals | AG16: 1 | AH16: 1 | AI16: 3
B17: Vitamins/Minerals | C17: =_xlfn.XLOOKUP(B17,'Analysis II'!M$4:M$17,'Analysis II'!N$4:N$17,0) -> A | D17: =_xlfn.XLOOKUP(B17,'Analysis II'!M$4:M$17,'Analysis II'!O$4:O$17,0) -> F | E17: High | F17: EOQ-based ordering | H17: Vitamins/Minerals | I17: =_xlfn.XLOOKUP(H17,'Analysis II'!D$23:D$36,'Analysis II'!F$23:F$36,0) -> 8.5 | J17: =_xlfn.XLOOKUP(H17,'Analysis II'!D$23:D$36,'Analysis II'!G$23:G$36,0) -> 51 | K17: =_xlfn.XLOOKUP(H17,'Analysis II'!D36:D49,'Analysis II'!H36:H49,0) -> 85
D21: Sum of Quantity | E21: Column Labels
D22: Row Labels | E22: Anti-microbial | F22: Baby Care | G22: Body Care | H22: Cardiovascular | I22: Cold/Cough | J22: Diabetes | K22: First Aid | L22: Gastro Tabs | M22: Immunosuppressant | N22: Pain Relief | O22: Respiratory | P22: Skincare | Q22: Sunscreen | R22: Vitamins/Minerals | S22: Grand Total | X22: Category | Y22: Std Dev of Demand
D23: 45931 | E23: 56 | G23: 1 | H23: 13 | I23: 1 | L23: 14 | P23: 12 | S23: 97 | X23: Anti-microbial | Y23: {=_xlfn.STDEV.S(IF(E23:E52="",0,E23:E52))} -> 30.540138
D24: 45932 | E24: 16 | F24: 2 | G24: 10 | H24: 8 | I24: 1 | J24: 5 | L24: 1 | N24: 22 | O24: 5 | P24: 17 | Q24: 3 | R24: 3 | S24: 93 | X24: Skincare | Y24: {=_xlfn.STDEV.S(IF(P23:P52="",0,P23:P52))} -> 10.902336
D25: 45933 | E25: 18 | F25: 2 | G25: 11 | H25: 11 | L25: 8 | O25: 10 | P25: 26 | R25: 29 | S25: 115 | X25: Pain Relief | Y25: {=_xlfn.STDEV.S(IF(N23:N52="",0,N23:N52))} -> 11.332235
D26: 45934 | E26: 4 | F26: 2 | G26: 2 | H26: 2 | L26: 1 | N26: 26 | P26: 7 | R26: 14 | S26: 58 | X26: Vitamins/Minerals | Y26: {=_xlfn.STDEV.S(IF(R23:R52="",0,R23:R52))} -> 9.4348949
D27: 45935 | E27: 158 | H27: 11 | I27: 10 | K27: 1 | L27: 38 | N27: 49 | P27: 1 | S27: 268 | X27: Cardiovascular | Y27: {=_xlfn.STDEV.S(IF(H23:H52="",0,H23:H52))} -> 7.7117614
D28: 45936 | E28: 17 | G28: 5 | H28: 12 | J28: 1 | L28: 11 | N28: 16 | O28: 30 | P28: 18 | R28: 9 | S28: 119 | X28: Body Care | Y28: {=_xlfn.STDEV.S(IF(G23:G52="",0,G23:G52))} -> 7.3659671
D29: 45937 | E29: 5 | G29: 2 | H29: 3 | I29: 17 | J29: 3 | M29: 2 | N29: 15 | P29: 2 | R29: 25 | S29: 74 | X29: Gastro Tabs | Y29: {=_xlfn.STDEV.S(IF(L23:L52="",0,L23:L52))} -> 7.6043696
D30: 45938 | E30: 30 | G30: 17 | H30: 20 | J30: 19 | K30: 6 | L30: 7 | N30: 18 | O30: 1 | P30: 3 | R30: 5 | S30: 126 | X30: Respiratory | Y30: {=_xlfn.STDEV.S(IF(O23:O52="",0,O23:O52))} -> 9.0063196
D31: 45939 | E31: 14 | H31: 6 | I31: 1 | L31: 7 | M31: 12 | P31: 8 | S31: 48 | X31: Diabetes | Y31: {=_xlfn.STDEV.S(IF(J23:J52="",0,J23:J52))} -> 4.5218499
D32: 45940 | G32: 13 | L32: 1 | N32: 2 | O32: 16 | P32: 18 | Q32: 2 | S32: 52 | X32: Cold/Cough | Y32: {=_xlfn.STDEV.S(IF(I23:I52="",0,I23:I52))} -> 4.0826237
D33: 45941 | E33: 7 | G33: 2 | H33: 8 | I33: 1 | J33: 1 | L33: 1 | N33: 1 | O33: 1 | P33: 5 | R33: 10 | S33: 37 | X33: First Aid | Y33: {=_xlfn.STDEV.S(IF(K23:K52="",0,K23:K52))} -> 1.6120951
D34: 45942 | E34: 3 | G34: 1 | J34: 2 | N34: 6 | P34: 12 | R34: 6 | S34: 30 | X34: Sunscreen | Y34: {=_xlfn.STDEV.S(IF(Q23:Q52="",0,Q23:Q52))} -> 1.2359556
D35: 45943 | G35: 1 | H35: 33 | J35: 2 | K35: 6 | N35: 10 | O35: 3 | P35: 3 | Q35: 2 | R35: 5 | S35: 65 | X35: Immunosuppressant | Y35: {=_xlfn.STDEV.S(IF(M23:M52="",0,M23:M52))} -> 2.2089161
D36: 45944 | E36: 7 | G36: 2 | H36: 3 | I36: 3 | J36: 2 | K36: 1 | L36: 1 | N36: 2 | O36: 38 | P36: 3 | R36: 6 | S36: 68 | X36: Baby Care | Y36: {=_xlfn.STDEV.S(IF(F23:F52="",0,F23:F52))} -> 1.0726485
D37: 45945 | E37: 2 | I37: 1 | L37: 1 | M37: 1 | N37: 2 | P37: 7 | R37: 7 | S37: 21
D38: 45946 | E38: 40 | P38: 25 | Q38: 5 | R38: 5 | S38: 75
D39: 45947 | E39: 25 | G39: 5 | P39: 20 | R39: 5 | S39: 55
D40: 45948 | E40: 1 | G40: 5 | H40: 5 | J40: 11 | N40: 4 | P40: 8 | R40: 17 | S40: 51
D41: 45949 | E41: 7 | G41: 24 | H41: 2 | K41: 3 | L41: 4 | N41: 4 | O41: 1 | P41: 12 | Q41: 2 | R41: 2 | S41: 61
D42: 45950 | G42: 1 | H42: 3 | J42: 11 | N42: 3 | P42: 6 | Q42: 2 | S42: 26
D43: 45951 | E43: 2 | G43: 19 | H43: 9 | I43: 1 | J43: 6 | N43: 30 | P43: 11 | Q43: 2 | R43: 33 | S43: 113
D44: 45952 | E44: 1 | I44: 1 | J44: 2 | K44: 1 | L44: 2 | N44: 5 | O44: 1 | P44: 12 | Q44: 1 | R44: 21 | S44: 47
D45: 45953 | E45: 14 | F45: 1 | G45: 4 | H45: 5 | K45: 2 | L45: 13 | N45: 5 | P45: 3 | R45: 25 | S45: 72
D46: 45954 | E46: 52 | H46: 2 | K46: 2 | L46: 2 | P46: 18 | S46: 76
D47: 45955 | E47: 13 | F47: 5 | G47: 11 | H47: 21 | I47: 1 | J47: 10 | L47: 1 | N47: 17 | P47: 3 | R47: 3 | S47: 85
D48: 45956 | E48: 21 | G48: 6 | J48: 3 | N48: 1 | P48: 5 | R48: 5 | S48: 41
D49: 45957 | E49: 54 | G49: 8 | H49: 3 | I49: 1 | J49: 7 | L49: 5 | P49: 6 | R49: 7 | S49: 91
D50: 45958 | E50: 20 | F50: 1 | G50: 27 | I50: 1 | J50: 4 | N50: 10 | O50: 5 | P50: 3 | Q50: 2 | R50: 12 | S50: 85
D51: 45959 | E51: 16 | G51: 4 | I51: 13 | K51: 1 | L51: 1 | N51: 5 | P51: 11 | S51: 51
D52: 45960 | E52: 18 | G52: 3 | H52: 10 | J52: 2 | N52: 12 | P52: 56 | R52: 1 | S52: 102
D53: Grand Total | E53: 621 | F53: 13 | G53: 184 | H53: 190 | I53: 53 | J53: 91 | K53: 23 | L53: 119 | M53: 15 | N53: 265 | O53: 111 | P53: 341 | Q53: 21 | R53: 255 | S53: 2302

Sheet Categorical Sales Value
A3: Row Labels | B3: Sum of Net Value
A4: Anti-microbial | B4: 87656.09 | C4: =B4/B$18 -> 0.20662648
A5: Baby Care | B5: 2858.11 | C5: =B5/B$18 -> 0.0067372525 | Q5: Row Labels | R5: Sum of Quantity
A6: Body Care | B6: 68741.59 | C6: =B6/B$18 -> 0.16204046 | Q6: Anti-microbial | R6: 621
A7: Cardiovascular | B7: 20768.13 | C7: =B7/B$18 -> 0.048955476 | Q7: Baby Care | R7: 13
A8: Cold/Cough | B8: 7530.95 | C8: =B8/B$18 -> 0.01775226 | Q8: Body Care | R8: 184
A9: Diabetes | B9: 12331.55 | C9: =B9/B$18 -> 0.029068428 | Q9: Cardiovascular | R9: 190
A10: First Aid | B10: 3158.16 | C10: =B10/B$18 -> 0.0074445425 | Q10: Cold/Cough | R10: 53
A11: Gastro Tabs | B11: 11714.39 | C11: =B11/B$18 -> 0.027613634 | Q11: Diabetes | R11: 91
A12: Immunosuppressant | B12: 1722.82 | C12: =B12/B$18 -> 0.004061101 | Q12: First Aid | R12: 23
A13: Pain Relief | B13: 25688.45 | C13: =B13/B$18 -> 0.060553853 | Q13: Gastro Tabs | R13: 119
A14: Respiratory | B14: 11057.12 | C14: =B14/B$18 -> 0.026064291 | Q14: Immunosuppressant | R14: 15
A15: Skincare | B15: 130075.75 | C15: =B15/B$18 -> 0.30661982 | Q15: Pain Relief | R15: 265
A16: Sunscreen | B16: 13624.1 | C16: =B16/B$18 -> 0.03211528 | Q16: Respiratory | R16: 111
A17: Vitamins/Minerals | B17: 27297.65 | C17: =B17/B$18 -> 0.064347125 | Q17: Skincare | R17: 341
A18: Grand Total | B18: 424224.86 | Q18: Sunscreen | R18: 21
Q19: Vitamins/Minerals | R19: 255
Q20: (blank)
Q21: Grand Total | R21: 2302
Q25: ANTI-MICROBIAL :REVENUE CONTRIBUTION
Q26: =B4/B18 -> 0.20662648
Q28: SKINCARE:REVENUE CONTRIBUTION
Q29: =B15/B18 -> 0.30661982
E38: Row Labels | F38: Sum of Total Profit | K38: Category | L38: Profit | M38: Cummulative %
E39: Anti-microbial | F39: 8054.0291 | K39: Anti-microbial | L39: 8054.0291 | M39: =L39/L$55 -> 0.2206139
E40: Baby Care | F40: 227.65909 | K40: Baby Care | L40: 227.65909 | M40: =L40/L$55 -> 0.0062359793
E41: Body Care | F41: 6109.3527 | K41: Body Care | L41: 6109.3527 | M41: =L41/L$55 -> 0.16734582
E42: Cardiovascular | F42: 2008.3809 | K42: Cardiovascular | L42: 2008.3809 | M42: =L42/L$55 -> 0.055013054
E43: Cold/Cough | F43: 672.40091 | K43: Cold/Cough | L43: 672.40091 | M43: =L43/L$55 -> 0.018418233
E44: Diabetes | F44: 1103.5073 | K44: Diabetes | L44: 1103.5073 | M44: =L44/L$55 -> 0.030226988
E45: First Aid | F45: 286.96545 | K45: First Aid | L45: 286.96545 | M45: =L45/L$55 -> 0.007860484
E46: Gastro Tabs | F46: 1044.4282 | K46: Gastro Tabs | L46: 1044.4282 | M46: =L46/L$55 -> 0.028608708
E47: Immunosuppressant | F47: 153.77727 | K47: Immunosuppressant | L47: 153.77727 | M47: =L47/L$55 -> 0.0042122275
E48: Pain Relief | F48: 1942.8609 | K48: Pain Relief | L48: 1942.8609 | M48: =L48/L$55 -> 0.053218347
E49: Respiratory | F49: 1016.7791 | K49: Respiratory | L49: 1016.7791 | M49: =L49/L$55 -> 0.027851352
E50: Skincare | F50: 10298.005 | K50: Skincare | L50: 10298.005 | M50: =L50/L$55 -> 0.28208032
... E52: Vitamins/Minerals | F52: 2455.64 | K52: Vitamins/Minerals | L52: 2455.64 | M52: =L52/L$55 -> 0.06726426
E53: (blank)
E54: Grand Total | F54: 36507.352
L55: =SUM(L39:L52) -> 36507.352

Sheet Daily Revenue analysis 
A3: Row Labels | B3: Sum of Net Value | D3: Row Labels | E3: Sum of Total Profit
A4: 45931 | B4: 15773.65 | D4: 45931 | E4: 1397.0109
A5: 45932 | B5: 19290.97 | D5: 45932 | E5: 1654.6527
A6: 45933 | B6: 20851.16 | D6: 45933 | E6: 1852.9018 | P6: Date | Q6: Revenue
A7: 45934 | B7: 8258.66 | D7: 45934 | E7: 711.82273 | P7: 45937 | Q7: =AVERAGE(E4:E10) -> 1195.1597
A8: 45935 | B8: 7769.28 | D8: 45935 | E8: 682.22636 | M8: Week Number | N8: Weekly Based Revenue | P8: 45938 | Q8: =AVERAGE(E5:E11) -> 1251.0138
A9: 45936 | B9: 17459.33 | D9: 45936 | E9: 1538.2891 | G9: Day when maximum revenue was generated | H9: =MAX(B4:B33) -> 38237.3 | I9: 45946 | M9: WEEK I | N9: =SUM(B4:B10) -> 95331.79 | P9: 45939 | Q9: =AVERAGE(E6:E12) -> 1167.941
A10: 45937 | B10: 5928.74 | D10: 45937 | E10: 529.21455 | G10: Day when maximum profit was generated | H10: =MAX(E4:E33) -> 3289.4636 | I10: 45946 | M10: WEEK II | N10: =SUM(B11:B17) -> 73971.7 | P10: 45940 | Q10: =AVERAGE(E7:E13) -> 1034.5792
A11: 45938 | B11: 20442.56 | D11: 45938 | E11: 1787.9891 | G11: Average daily sale | H11: =AVERAGE(B4:B33) -> 14140.829 | M11: WEEK III | N11: =SUM(B18:B24) -> 123452.13 | P11: 45941 | Q11: =AVERAGE(E8:E14) -> 1012.0068
A12: 45939 | B12: 11925.07 | D12: 45939 | E12: 1073.1436 | M12: WEEK IV | N12: =SUM(B25:B33) -> 131469.24 | P12: 45942 | Q12: =AVERAGE(E9:E15) -> 1008.1705
A13: 45940 | B13: 10325.66 | D13: 45940 | E13: 919.36909 | G13: Day when minimum revenue was generated | H13: =MIN(B4:B33) -> 5640.7 | I13: 45950 | P13: 45943 | Q13: =AVERAGE(E10:E16) -> 914.06234
A14: 45941 | B14: 6373.45 | D14: 45941 | E14: 553.81545 | G14: Day when minimum profit was generated | H14: =MIN(E4:E33) -> 342.72727 | I14: 45945 | P14: 45944 | Q14: =AVERAGE(E11:E17) -> 935.48584
A15: 45942 | B15: 7776.58 | D15: 45942 | E15: 655.37273 | G15: Total Revenue generated | H15: =B35 -> 424224.86 | P15: 45945 | Q15: =AVERAGE(E12:E18) -> 729.01987
A16: 45943 | B16: 9363.33 | D16: 45943 | E16: 879.53182 | G16: Total Profit generated | H16: =SUM(E4:E33) -> 36507.352 | P16: 45946 | Q16: =AVERAGE(E13:E19) -> 1045.637
A17: 45944 | B17: 7765.05 | D17: 45944 | E17: 679.17909 | P17: 45947 | Q17: =AVERAGE(E14:E20) -> 1283.1447
A18: 45945 | B18: 16041.49 | D18: 45945 | E18: 342.72727 | P18: 45948 | Q18: =AVERAGE(E15:E21) -> 1352.9427
A19: 45946 | B19: 38237.3 | D19: 45946 | E19: 3289.4636 | P19: 45949 | Q19: =AVERAGE(E16:E22) -> 1376.4975
A20: 45947 | B20: 28401.15 | D20: 45947 | E20: 2581.9227 | P20: 45950 | Q20: =AVERAGE(E17:E23) -> 1317.1447
A21: 45948 | B21: 11469.46 | D21: 45948 | E21: 1042.4018 | P21: 45951 | Q21: =AVERAGE(E18:E24) -> 1403.3747
A22: 45949 | B22: 9418.98 | D22: 45949 | E22: 820.25636 | P22: 45952 | Q22: =AVERAGE(E19:E25) -> 1441.4278
A23: 45950 | B23: 5640.7 | D23: 45950 | E23: 464.06182 | P23: 45953 | Q23: =AVERAGE(E20:E26) -> 1080.4744
A24: 45951 | B24: 14243.05 | D24: 45951 | E24: 1282.7891 | P24: 45954 | Q24: =AVERAGE(E21:E27) -> 908.08649
A25: 45952 | B25: 6881.67 | D25: 45952 | E25: 609.09909 | P25: 45955 | Q25: =AVERAGE(E22:E28) -> 887.21831
A26: 45953 | B26: 8834.09 | D26: 45953 | E26: 762.79 | P26: 45956 | Q26: =AVERAGE(E23:E29) -> 895.9113
A27: 45954 | B27: 12738.24 | D27: 45954 | E27: 1375.2073 | P27: 45957 | Q27: =AVERAGE(E24:E30) -> 1112.79
A28: 45955 | B28: 10164.48 | D28: 45955 | E28: 896.32455 | P28: 45958 | Q28: =AVERAGE(E25:E31) -> 1306.7329
... A30: 45957 | B30: 22478.97 | D30: 45957 | E30: 1982.2127 | P30: 45960 | Q30: =AVERAGE(E27:E33) -> 1485.3316
A31: 45958 | B31: 29421.74 | D31: 45958 | E31: 2640.3891
A32: 45959 | B32: 12056.37 | D32: 45959 | E32: 750.99182
A33: 45960 | B33: 18938.18 | D33: 45960 | E33: 1871.0882
A34: (blank) | D34: Grand Total | E34: 36507.352
A35: Grand Total | B35: 424224.86
A37: Date | B37: Revenue
A38: 45931 | B38: 15773.65
A39: 45933 | B39: 20851.16
A40: 45935 | B40: 7769.28
A41: 45937 | B41: 5928.74
A42: 45939 | B42: 11925.07
A43: 45941 | B43: 6373.45
A44: 45943 | B44: 9363.33
A45: 45945 | B45: 16041.49
A46: 45947 | B46: 28401.15
A47: 45949 | B47: 9418.98
A48: 45951 | B48: 14243.05
A49: 45953 | B49: 8834.09
... A52: 45959 | B52: 12056.37

Sheet Expiry products Analysis
A3: Row Labels | B3: Sum of Quantity | D3: Category | E3: Quantity | I3: Row Labels | J3: Sum of Total | K3: Percentage of Loss
A4: Anti-microbial | B4: 25 | D4: Anti-microbial | E4: 25 | I4: Anti-microbial | J4: 4379.7 | K4: =J4/J$14 -> 0.044939644 | R4: Category | S4: Revenue Generated | T4: Loss Incurred
A5: Cardiovascular | B5: 80 | D5: Cardiovascular | E5: 80 | I5: Cardiovascular | J5: 7096.3 | K5: =J5/J$14 -> 0.072814393 | N5: Total Expired Loss | O5: =SUM(J4:J13) -> 97457.38 | R5: Anti-microbial | S5: =_xlfn.XLOOKUP(R5,'Categorical Sales Value'!A$4:A$17,'Categorical Sales Value'!B$4:B$17,0) -> 87656.09 | T5: 4379.7
A6: Cold/Cough | B6: 15 | D6: Cold | E6: 15 | I6: Cold/Cough | J6: 2006.25 | K6: =J6/J$14 -> 0.020585922 | N6: % of Expired | O6: =J14/'Daily Revenue analysis '!H15 -> 0.22973048 | R6: Cardiovascular | S6: =_xlfn.XLOOKUP(R6,'Categorical Sales Value'!A$4:A$17,'Categorical Sales Value'!B$4:B$17,0) -> 20768.13 | T6: 7096.3
A7: Diabetes | B7: 49 | D7: Diabetes | E7: 49 | I7: Diabetes | J7: 7284 | K7: =J7/J$14 -> 0.074740363 | R7: Cold/Cough | S7: =_xlfn.XLOOKUP(R7,'Categorical Sales Value'!A$4:A$17,'Categorical Sales Value'!B$4:B$17,0) -> 7530.95 | T7: 2006.25
A8: Pain Relief | B8: 65 | D8: Pain Relief | E8: 65 | I8: Pain Relief | J8: 11063.17 | K8: =J8/J$14 -> 0.11351803 | R8: Diabetes | S8: =_xlfn.XLOOKUP(R8,'Categorical Sales Value'!A$4:A$17,'Categorical Sales Value'!B$4:B$17,0) -> 12331.55 | T8: 7284
A9: Skincare | B9: 40 | D9: Skincare | E9: 40 | I9: Skincare | J9: 11404.88 | K9: =J9/J$14 -> 0.11702428 | R9: Pain Relief | S9: =_xlfn.XLOOKUP(R9,'Categorical Sales Value'!A$4:A$17,'Categorical Sales Value'!B$4:B$17,0) -> 25688.45 | T9: 11063.17
A10: Sunscreen | B10: 8 | D10: Sunscreen | E10: 8 | I10: Sunscreen | J10: 6800 | K10: =J10/J$14 -> 0.06977409 | R10: Skincare | S10: =_xlfn.XLOOKUP(R10,'Categorical Sales Value'!A$4:A$17,'Categorical Sales Value'!B$4:B$17,0) -> 130075.75 | T10: 11404.88
A11: Vitamins/Minerals | B11: 19 | D11: Vitamins | E11: 19 | I11: Vitamins/Minerals | J11: 4800 | K11: =J11/J$14 -> 0.049252299 | R11: Sunscreen | S11: =_xlfn.XLOOKUP(R11,'Categorical Sales Value'!A$4:A$17,'Categorical Sales Value'!B$4:B$17,0) -> 13624.1 | T11: 6800
A12: Immunosuppresant | B12: 230 | D12: Immunosuppresant | E12: 230 | I12: Immunosuppresant | J12: 41434.28 | K12: =J12/J$14 -> 0.42515282 | R12: Vitamins/Minerals | S12: =_xlfn.XLOOKUP(R12,'Categorical Sales Value'!A$4:A$17,'Categorical Sales Value'!B$4:B$17,0) -> 27297.65 | T12: 4800
A13: Gastro Tabs | B13: 22 | D13: Gastro Tabs | E13: 22 | I13: Gastro Tabs | J13: 1188.8 | K13: =J13/J$14 -> 0.012198153 | R13: Immunosuppressant | S13: 1722.82 | T13: 41434.28
A14: Grand Total | B14: 553 | I14: Grand Total | J14: 97457.38 | R14: Gastro Tabs | S14: =_xlfn.XLOOKUP(R14,'Categorical Sales Value'!A$4:A$17,'Categorical Sales Value'!B$4:B$17,0) -> 11714.39 | T14: 1188.8
K17: LOSS DUE TO SKINCARE
K18: =J10/J14 -> 0.06977409
K20: LOSS DUE TO IMMUNOSUPPRESSANT
K21: =J13/J14 -> 0.012198153
